{"adult":false,"backdrop_path":"\/lR71zfC8uQjEloVAVicsAogZl6E.jpg","belongs_to_collection":null,"budget":25000000,"genres":[{"id":10749,"name":"Romance"},{"id":35,"name":"Comedy"}],"homepage":"http:\/\/www.thehousebunny.com\/","id":12620,"imdb_id":"tt0852713","original_language":"en","original_title":"The House Bunny","overview":"Shelley is living a carefree life until a rival gets her tossed out of the Playboy Mansion. With nowhere to go, fate delivers her to the sorority girls from Zeta Alpha Zeta. Unless they can sign a new pledge class, the seven socially clueless women will lose their house to the scheming girls of Phi Iota Mu. In order to accomplish their goal, they need Shelley to teach them the ways of makeup and men; at the same time, Shelley needs some of what the Zetas have - a sense of individuality. The combination leads all the girls to learn how to stop pretending and start being themselves.","popularity":2.034617,"poster_path":"\/r4QlWdvduWGJdiGlYiwIsDC1kPu.jpg","production_companies":[{"name":"Columbia Pictures","id":5},{"name":"Happy Madison Productions","id":2608},{"name":"Relativity Media","id":7295},{"name":"Alta Loma Entertainment","id":15636}],"production_countries":[{"iso_3166_1":"US","name":"United States of America"}],"release_date":"2008-08-22","revenue":70442940,"runtime":97,"spoken_languages":[{"iso_639_1":"en","name":"English"}],"status":"Released","tagline":"For the girls of ZETA house college life was no party, until Shelley showed up.","title":"The House Bunny","video":false,"vote_average":5.5,"vote_count":282,"credits":{"cast":[{"cast_id":23,"character":"Shelley","credit_id":"52fe45099251416c75049795","id":1772,"name":"Anna Faris","order":0,"profile_path":"\/eHh3ZVEdBlXSBNjpHaGkGKvx1QI.jpg"},{"cast_id":2,"character":"Natalie","credit_id":"52fe45089251416c75049723","id":54693,"name":"Emma Stone","order":1,"profile_path":"\/xaVbkdhLThQZ5rQr1PCLzAgCEeB.jpg"},{"cast_id":3,"character":"Mona","credit_id":"52fe45089251416c75049727","id":52852,"name":"Kat Dennings","order":2,"profile_path":"\/axPn5eI5mlZtlZJWrvYRq1hCcUh.jpg"},{"cast_id":27,"character":"Harmony","credit_id":"52fe45099251416c750497a7","id":77088,"name":"Katharine McPhee","order":3,"profile_path":"\/qTlKrXgnQbMjf0pqz6mpdp0GLnK.jpg"},{"cast_id":7,"character":"Joanne","credit_id":"52fe45089251416c75049737","id":20848,"name":"Rumer Willis","order":4,"profile_path":"\/5e90ywK988FUuvwmoh5EVg2xPDT.jpg"},{"cast_id":4,"character":"Hugh Hefner","credit_id":"52fe45089251416c7504972b","id":31309,"name":"Hugh M. Hefner","order":5,"profile_path":"\/3BS3PEHxgqr7G1ItTpCGzhSFViV.jpg"},{"cast_id":5,"character":"Dean Simmons","credit_id":"52fe45089251416c7504972f","id":4443,"name":"Christopher McDonald","order":6,"profile_path":"\/ltaSSI1kGZGSii5W9dJM9kY8Ka.jpg"},{"cast_id":6,"character":"Mrs. Hagstrom","credit_id":"52fe45089251416c75049733","id":821,"name":"Beverly D'Angelo","order":7,"profile_path":"\/fkedkicdG9o9axNqGs5tcTFxglw.jpg"},{"cast_id":25,"character":"Lilly","credit_id":"52fe45099251416c7504979f","id":74046,"name":"Kiely Williams","order":8,"profile_path":"\/svjs9Rw3wYQzX8BNwBmvHGk4bAL.jpg"},{"cast_id":26,"character":"Colby","credit_id":"52fe45099251416c750497a3","id":74047,"name":"Tyson Ritter","order":9,"profile_path":"\/uavIDRS6SI5omz8AzstUsXpbPNz.jpg"},{"cast_id":28,"character":"Oliver","credit_id":"52fe45099251416c750497ab","id":3492,"name":"Colin Hanks","order":10,"profile_path":"\/jhdZWVUQZ71JVwuLdvxelvQmYDl.jpg"},{"cast_id":29,"character":"Ashley","credit_id":"52fe45099251416c750497af","id":131723,"name":"Sarah Wright","order":11,"profile_path":"\/fKsu9PJ4DuBVja60yKnvLgPHvq3.jpg"},{"cast_id":31,"character":"Girl at Panhellenic","credit_id":"562caf9792514128530079d6","id":1202550,"name":"Danni Katz","order":12,"profile_path":"\/mfzHgVRsDU3j2Tu41AK4N36R5NJ.jpg"},{"cast_id":32,"character":"Carrie Mae","credit_id":"56314d909251414ad800e981","id":214834,"name":"Dana Goodman","order":13,"profile_path":"\/58vNNkQp6LdMsfozKUutZL8uPIg.jpg"},{"cast_id":33,"character":"Tanya","credit_id":"56314e3b925141285700fffa","id":1528691,"name":"Kimberly Makkouk","order":14,"profile_path":"\/l1Am0oFqAHJWBesOdkX4mHJmJan.jpg"},{"cast_id":34,"character":"Cassandra","credit_id":"56314eeb925141284c010887","id":34844,"name":"Monet Mazur","order":15,"profile_path":"\/lvLC6Sjt8pETC3La8rGvhyYWSx0.jpg"},{"cast_id":36,"character":"Kip","credit_id":"57bdf2a4925141734c001ad4","id":1105796,"name":"Jay Hayden","order":16,"profile_path":"\/cGoz9A88fD333JE2CV7wWwfImYu.jpg"}],"crew":[{"credit_id":"52fe45089251416c7504973d","department":"Directing","id":66563,"job":"Director","name":"Fred Wolf","profile_path":null},{"credit_id":"52fe45089251416c75049743","department":"Writing","id":40589,"job":"Author","name":"Karen McCullah Lutz","profile_path":null},{"credit_id":"52fe45089251416c75049749","department":"Writing","id":40590,"job":"Author","name":"Kirsten Smith","profile_path":null},{"credit_id":"52fe45089251416c7504974f","department":"Production","id":20818,"job":"Producer","name":"Allen Covert","profile_path":"\/wpcbF6UZXJ5u4tuL4A72hAoqiNL.jpg"},{"credit_id":"52fe45089251416c75049755","department":"Production","id":1772,"job":"Executive Producer","name":"Anna Faris","profile_path":"\/eHh3ZVEdBlXSBNjpHaGkGKvx1QI.jpg"},{"credit_id":"52fe45089251416c7504975b","department":"Production","id":40589,"job":"Executive Producer","name":"Karen McCullah Lutz","profile_path":null},{"credit_id":"52fe45089251416c75049761","department":"Production","id":19292,"job":"Producer","name":"Adam Sandler","profile_path":"\/tv9V6QsuZ3bcp4ciUJjwjcc4qAg.jpg"},{"credit_id":"52fe45089251416c75049767","department":"Production","id":40590,"job":"Executive Producer","name":"Kirsten Smith","profile_path":null},{"credit_id":"52fe45089251416c7504976d","department":"Camera","id":4950,"job":"Director of Photography","name":"Shelly Johnson","profile_path":null},{"credit_id":"52fe45089251416c75049773","department":"Editing","id":57426,"job":"Editor","name":"Debra Chiate","profile_path":null},{"credit_id":"560a617ac3a3686817001f45","department":"Production","id":1516479,"job":"Casting","name":"Lisa London","profile_path":"\/mnz59WWGxSeWGr3cBkqBhqLTynj.jpg"},{"credit_id":"52fe45099251416c7504977f","department":"Art","id":6628,"job":"Production Design","name":"Missy Stewart","profile_path":null},{"credit_id":"52fe45099251416c75049785","department":"Art","id":39124,"job":"Set Decoration","name":"Tracey A. Doyle","profile_path":null},{"credit_id":"52fe45099251416c7504978b","department":"Costume & Make-Up","id":42909,"job":"Costume Design","name":"Mona May","profile_path":null},{"credit_id":"52fe45099251416c75049791","department":"Production","id":20821,"job":"Producer","name":"Jack Giarraputo","profile_path":null},{"credit_id":"52fe45099251416c7504979b","department":"Sound","id":60150,"job":"Music","name":"Waddy Wachtel","profile_path":null},{"credit_id":"56cee589c3a3681e39001da8","department":"Production","id":8288,"job":"Unit Production Manager","name":"Debra James","profile_path":null}]},"images":{"backdrops":[{"aspect_ratio":1.7784963621665,"file_path":"\/lR71zfC8uQjEloVAVicsAogZl6E.jpg","height":1237,"iso_639_1":null,"vote_average":5.3125,"vote_count":1,"width":2200},{"aspect_ratio":1.7777777777778,"file_path":"\/6ECZDtiEqSEpMOgz3HBG5N47fRW.jpg","height":1080,"iso_639_1":null,"vote_average":5.2454212454212,"vote_count":2,"width":1920},{"aspect_ratio":1.7777777777778,"file_path":"\/7dCStFGRVvRHzVzZylqrdol1H5.jpg","height":720,"iso_639_1":null,"vote_average":5.2454212454212,"vote_count":2,"width":1280},{"aspect_ratio":1.7777777777778,"file_path":"\/kH5CZPB5rnCVHqZSY8mZNd4Z0Vr.jpg","height":720,"iso_639_1":null,"vote_average":5.2454212454212,"vote_count":2,"width":1280},{"aspect_ratio":1.7777777777778,"file_path":"\/1TsBCZ05WJeXBFDU75gUSVMT7Z6.jpg","height":720,"iso_639_1":null,"vote_average":5.2454212454212,"vote_count":2,"width":1280},{"aspect_ratio":1.7777777777778,"file_path":"\/cM9sLtGuQB5LeiaqHnoS6XdUy6p.jpg","height":1080,"iso_639_1":null,"vote_average":5.2454212454212,"vote_count":2,"width":1920},{"aspect_ratio":1.7777777777778,"file_path":"\/iowW30haE6MYeZePGW6eOXHnlko.jpg","height":720,"iso_639_1":null,"vote_average":5.2307692307692,"vote_count":2,"width":1280},{"aspect_ratio":1.7777777777778,"file_path":"\/5dba8lGy6aDVNWoWvLjZyr9XQN1.jpg","height":720,"iso_639_1":null,"vote_average":5.2307692307692,"vote_count":2,"width":1280},{"aspect_ratio":1.7777777777778,"file_path":"\/qgnvFLkUtFBWU81qhzz5DgC7juT.jpg","height":720,"iso_639_1":null,"vote_average":5.2307692307692,"vote_count":2,"width":1280},{"aspect_ratio":1.7777777777778,"file_path":"\/nF1k2vcRtYCGtjCHivHlaDt3pC3.jpg","height":720,"iso_639_1":null,"vote_average":5.2307692307692,"vote_count":2,"width":1280},{"aspect_ratio":1.7777777777778,"file_path":"\/4YHdxPEMtIWp8leQ7xoMGuGqeOD.jpg","height":720,"iso_639_1":null,"vote_average":5.2307692307692,"vote_count":2,"width":1280},{"aspect_ratio":1.7777777777778,"file_path":"\/35TYJj3qi1gb3CZO1NsYltjFCU3.jpg","height":720,"iso_639_1":null,"vote_average":5.2087912087912,"vote_count":2,"width":1280},{"aspect_ratio":1.7777777777778,"file_path":"\/wXicuWeSzIYeDHm1j6IxPTyPwb1.jpg","height":720,"iso_639_1":null,"vote_average":5.1711309523809,"vote_count":1,"width":1280},{"aspect_ratio":1.7777777777778,"file_path":"\/d2pbvJkNAunv2NI7RYU1ejqZN7Z.jpg","height":1080,"iso_639_1":null,"vote_average":5.1711309523809,"vote_count":1,"width":1920},{"aspect_ratio":1.7777777777778,"file_path":"\/4WZqC8dpUq4nmQqqa8LRaOxxzAR.jpg","height":1080,"iso_639_1":null,"vote_average":0,"vote_count":0,"width":1920}],"posters":[{"aspect_ratio":0.66666666666667,"file_path":"\/r4QlWdvduWGJdiGlYiwIsDC1kPu.jpg","height":1500,"iso_639_1":"en","vote_average":5.3655264922871,"vote_count":8,"width":1000},{"aspect_ratio":0.66666666666667,"file_path":"\/vJPL2YUbX0FtmPtr7H9QIxfCchJ.jpg","height":1500,"iso_639_1":"de","vote_average":5.3125,"vote_count":1,"width":1000},{"aspect_ratio":0.70011668611435,"file_path":"\/u402LyPdJR0S2mCmfrxLqiyRKFO.jpg","height":1714,"iso_639_1":"it","vote_average":5.3125,"vote_count":1,"width":1200},{"aspect_ratio":0.66666666666667,"file_path":"\/6nvosT0oCrQ0koqwj0kiOVCwRPQ.jpg","height":1200,"iso_639_1":"en","vote_average":5.312,"vote_count":1,"width":800},{"aspect_ratio":0.66666666666667,"file_path":"\/iRLEr1TvlioCAg2s1unFemmNhcv.jpg","height":1431,"iso_639_1":"en","vote_average":5.312,"vote_count":1,"width":954},{"aspect_ratio":0.69376693766938,"file_path":"\/wmGwlZaS38z2stUnPpdRkcLVqel.jpg","height":1476,"iso_639_1":"es","vote_average":5.2454212454212,"vote_count":2,"width":1024},{"aspect_ratio":0.67236328125,"file_path":"\/nMLiVx0n6WrkS796y4pMWLluUG7.jpg","height":2048,"iso_639_1":"en","vote_average":5.181236673774,"vote_count":4,"width":1377},{"aspect_ratio":0.69513406156902,"file_path":"\/a19xIFygvUewHFIyCAjxYrfcB5.jpg","height":1007,"iso_639_1":"he","vote_average":5.1711309523809,"vote_count":1,"width":700},{"aspect_ratio":0.72727272727273,"file_path":"\/yMGyZpe6pwOOplPUO1UZnQdn73o.jpg","height":1100,"iso_639_1":"ru","vote_average":5.1711309523809,"vote_count":1,"width":800},{"aspect_ratio":0.75,"file_path":"\/8wdXKIqTcsOAvX4rrZYp5Aypjwp.jpg","height":800,"iso_639_1":"fr","vote_average":5.1711309523809,"vote_count":1,"width":600},{"aspect_ratio":0.675,"file_path":"\/yHtMA1ynFJxK1pxdhrlyqr6OWcQ.jpg","height":1000,"iso_639_1":"en","vote_average":5.1172707889126,"vote_count":4,"width":675},{"aspect_ratio":0.70483870967742,"file_path":"\/bTQtisXQBB58xnRGfrUHpmK5jMR.jpg","height":2480,"iso_639_1":"de","vote_average":5.1062271062271,"vote_count":2,"width":1748},{"aspect_ratio":0.69991251093613,"file_path":"\/lB7gLVJLhWU7cQ92LS2dscwRjyz.jpg","height":1143,"iso_639_1":"it","vote_average":5.0604122245913,"vote_count":4,"width":800},{"aspect_ratio":0.6675,"file_path":"\/nOvlPmoZCqUKeYpF652VFJKu1EZ.jpg","height":800,"iso_639_1":"ja","vote_average":0,"vote_count":0,"width":534},{"aspect_ratio":0.66581632653061,"file_path":"\/cQ8S3KMrr7gl6azrM70RoiyXHHJ.jpg","height":784,"iso_639_1":"nl","vote_average":0,"vote_count":0,"width":522},{"aspect_ratio":0.6664290805417,"file_path":"\/AoHhJo7YuZkAufgMOcieQAc7gK.jpg","height":2806,"iso_639_1":"ro","vote_average":0,"vote_count":0,"width":1870}]}}