{"adult":false,"backdrop_path":"\/iB0RsWVoOXzicPi2Yy5xmTYMbho.jpg","belongs_to_collection":{"id":363369,"name":"Pacific Rim Collection","poster_path":"\/niTMK5k486sPBCphbvmRIZ7xBGK.jpg","backdrop_path":"\/vbg4Mm8auNINPersFlYvyGLqFq0.jpg"},"budget":180000000,"genres":[{"id":28,"name":"Action"},{"id":878,"name":"Science Fiction"},{"id":12,"name":"Adventure"}],"homepage":"http:\/\/www.pacificrimmovie.com\/","id":68726,"imdb_id":"tt1663662","original_language":"en","original_title":"Pacific Rim","overview":"When legions of monstrous creatures, known as Kaiju, started rising from the sea, a war began that would take millions of lives and consume humanity's resources for years on end. To combat the giant Kaiju, a special type of weapon was devised: massive robots, called Jaegers, which are controlled simultaneously by two pilots whose minds are locked in a neural bridge. But even the Jaegers are proving nearly defenseless in the face of the relentless Kaiju. On the verge of defeat, the forces defending mankind have no choice but to turn to two unlikely heroes\u2014a washed-up former pilot (Charlie Hunnam) and an untested trainee (Rinko Kikuchi)\u2014who are teamed to drive a legendary but seemingly obsolete Jaeger from the past. Together, they stand as mankind's last hope against the mounting apocalypse.","popularity":3.166958,"poster_path":"\/sCJEwEShZvruTpQ2a4yiX3Q9EyZ.jpg","production_companies":[{"name":"Legendary Pictures","id":923},{"name":"Warner Bros.","id":6194},{"name":"Disney Double Dare You (DDY)","id":19750},{"name":"Indochina Productions","id":19751}],"production_countries":[{"iso_3166_1":"US","name":"United States of America"},{"iso_3166_1":"CA","name":"Canada"}],"release_date":"2013-07-11","revenue":407602906,"runtime":131,"spoken_languages":[{"iso_639_1":"en","name":"English"}],"status":"Released","tagline":"To Fight Monsters, We Created Monsters","title":"Pacific Rim","video":false,"vote_average":6.7,"vote_count":3461,"credits":{"cast":[{"cast_id":2,"character":"Stacker Pentecost","credit_id":"52fe47a0c3a368484e0d1845","id":17605,"name":"Idris Elba","order":0,"profile_path":"\/4fuJRkT2TdfznRONUvQmdcayTTx.jpg"},{"cast_id":3,"character":"Raleigh Becket","credit_id":"52fe47a0c3a368484e0d1849","id":56365,"name":"Charlie Hunnam","order":1,"profile_path":"\/bZD3r5pzCMrqGrQksCdxfkmQ7ur.jpg"},{"cast_id":4,"character":"Dr. Newton Geiszler","credit_id":"52fe47a0c3a368484e0d184d","id":95101,"name":"Charlie Day","order":2,"profile_path":"\/irtCEk7XlszzNzAEwzQNtW27VsM.jpg"},{"cast_id":6,"character":"Hannibal Chau","credit_id":"52fe47a0c3a368484e0d1857","id":2372,"name":"Ron Perlman","order":3,"profile_path":"\/xZyrXT2iEmSOokQRc1hedmxrbTi.jpg"},{"cast_id":7,"character":"Gottlieb","credit_id":"52fe47a0c3a368484e0d185b","id":39659,"name":"Burn Gorman","order":4,"profile_path":"\/6q3YzYjnuAScnTHUag1xNkWQJTE.jpg"},{"cast_id":8,"character":"Mako Mori","credit_id":"52fe47a0c3a368484e0d185f","id":18054,"name":"Rinko Kikuchi","order":5,"profile_path":"\/lORc0Kwv1pd5LTIrm2xNiqsLy70.jpg"},{"cast_id":9,"character":"Herc Hansen","credit_id":"52fe47a0c3a368484e0d1863","id":94864,"name":"Max Martini","order":6,"profile_path":"\/fUGKNDsQnKCLzNrWyyBkx7O26XC.jpg"},{"cast_id":10,"character":"Aleksis Kaidanovsky","credit_id":"52fe47a0c3a368484e0d1867","id":112692,"name":"Robert Maillet","order":7,"profile_path":"\/cmP2CakmT1j0wXAjNEVQMGcR0cL.jpg"},{"cast_id":11,"character":"Chuck Hansen","credit_id":"52fe47a0c3a368484e0d186b","id":1038379,"name":"Robert Kazinsky","order":8,"profile_path":"\/h54Qs5LK19NT2ZA2ysRzjjnuODH.jpg"},{"cast_id":12,"character":"Tommy T","credit_id":"52fe47a0c3a368484e0d186f","id":118590,"name":"Larry Joe Campbell","order":9,"profile_path":"\/91kXO2XCIv8B9bP3720QIrTJNfs.jpg"},{"cast_id":13,"character":"Miles","credit_id":"52fe47a0c3a368484e0d1873","id":15376,"name":"Brad William Henke","order":10,"profile_path":"\/mrczPKKtc6a2AuVAdjqLLTnWhh5.jpg"},{"cast_id":14,"character":"Ops Tendo Choi","credit_id":"52fe47a0c3a368484e0d1877","id":5365,"name":"Clifton Collins, Jr.","order":11,"profile_path":"\/4gt2oqy6SjJxlbUgKIEbpQrEwas.jpg"},{"cast_id":15,"character":"Yancy Becket","credit_id":"52fe47a0c3a368484e0d187b","id":142193,"name":"Diego Klattenhoff","order":12,"profile_path":"\/nOiJDYiEysyZJHQNPCOSVWw9XzT.jpg"},{"cast_id":16,"character":"Wizened Man","credit_id":"52fe47a0c3a368484e0d187f","id":10847,"name":"Santiago Segura","order":13,"profile_path":"\/lNWgadL9NksUCdSaiJRDBRsT8oB.jpg"},{"cast_id":38,"character":"Raleigh and Yancy's Mom","credit_id":"54e49936c3a368486f003000","id":1428550,"name":"Jane Watson","order":14,"profile_path":"\/8wMVQt7Xp2dQUu3wnkc0wiETfJk.jpg"},{"cast_id":44,"character":"Hannibal Chau Thug","credit_id":"566109bcc3a36875e00062eb","id":1480855,"name":"Jung-Yul Kim","order":15,"profile_path":"\/yfXZoDUHQeTKLctbliF1TlqlmLH.jpg"},{"cast_id":45,"character":"Lt. A. Kaidanovsky","credit_id":"566109e0c3a36875e2005bd4","id":83423,"name":"Heather Doerksen","order":16,"profile_path":"\/nIF1GLQ2WPGS5pdogVGhOm2nYmh.jpg"},{"cast_id":46,"character":"Officer","credit_id":"56610a10c3a36875f40057a1","id":5925,"name":"Joshua Peace","order":17,"profile_path":"\/C5xx4dU6NtB7vzoX9Ho6p7CgOb.jpg"},{"cast_id":49,"character":"Young Mako","credit_id":"57e52b3a9251411ab00024f0","id":559416,"name":"Mana Ashida","order":18,"profile_path":"\/gvfweKd6XU3AQy1CFakbVNYeMCI.jpg"},{"cast_id":50,"character":"Captain Merrit","credit_id":"57e52bc3c3a36826a7002c30","id":86237,"name":"Joe Pingue","order":19,"profile_path":"\/4ePqYUDKEh0Fxa2s7bfzoCpmsCK.jpg"},{"cast_id":51,"character":"McTighe","credit_id":"57e52e8ac3a368264b0032d4","id":1226806,"name":"Milton Barnes","order":20,"profile_path":"\/8Lb9cegevGfADPuZNQ1BWunisik.jpg"},{"cast_id":52,"character":"1st Officer","credit_id":"57e52f059251411af40028a5","id":100464,"name":"Brian Frank","order":21,"profile_path":null},{"cast_id":53,"character":"Gipsy Danger AI (voice)","credit_id":"57e52f64c3a3684ca5004c02","id":1683877,"name":"Ellen McLain","order":22,"profile_path":null},{"cast_id":54,"character":"Old Man on Beach","credit_id":"57e53568c3a3684ca5004ea6","id":4569,"name":"David Fox","order":23,"profile_path":null},{"cast_id":55,"character":"Child","credit_id":"57e535f3c3a36841e5002d2a","id":1255174,"name":"Jake Goodman","order":24,"profile_path":null},{"cast_id":56,"character":"American UN Representative","credit_id":"57e53821c3a36841e5002ea0","id":41465,"name":"Robin Thomas","order":25,"profile_path":"\/oGIOvKZ1dlKhPWxU89exJVZhusV.jpg"},{"cast_id":57,"character":"British UN Representative","credit_id":"57e53df89251411ab0002e05","id":1379395,"name":"Julian Barnes","order":26,"profile_path":"\/nBxDyUCuJHkbOv008KrsLYd9E5D.jpg"},{"cast_id":58,"character":"Canadian UN Representative (as David Richmond Peck)","credit_id":"57e53e73c3a36841ae002b1e","id":46906,"name":"David Richmond-Peck","order":27,"profile_path":"\/1htiOvFIdq2vhqZLrz9kWOY3Dd6.jpg"},{"cast_id":59,"character":"Engineer","credit_id":"57e53fb592514106020038bf","id":224144,"name":"Sebastian Pigott","order":28,"profile_path":"\/d7e1X9vd7W63tTl9CoodMegJwSX.jpg"},{"cast_id":60,"character":"Chinese Girl in Anti-Kaiju Refuge","credit_id":"57e541309251410611003888","id":1683916,"name":"Victoria Marie","order":29,"profile_path":null},{"cast_id":61,"character":"TV Reporter (as JC Kenny)","credit_id":"57e543c1c3a368264b003e61","id":1176955,"name":"J.C. Kenny","order":30,"profile_path":null},{"cast_id":62,"character":"Raleigh and Yancy's Dad","credit_id":"57e546139251410602003bd8","id":1683922,"name":"Robert Morse","order":31,"profile_path":null},{"cast_id":63,"character":"Saltchuck Crew","credit_id":"57e5476ac3a36826a70038a4","id":59613,"name":"Mike Chute","order":32,"profile_path":"\/yDjnDYaxYz02HCpmcIEJ8leq5PQ.jpg"},{"cast_id":64,"character":"Saltchuck Crew","credit_id":"57e54bb4c3a3684ca50058e3","id":1683931,"name":"Duncan McLeod","order":33,"profile_path":null},{"cast_id":65,"character":"Saltchuck Crew","credit_id":"57e5502c925141064e00400e","id":1517893,"name":"Louis Paquette","order":34,"profile_path":null},{"cast_id":66,"character":"Saltchuck Crew","credit_id":"57e5506ac3a36826a7003c65","id":59198,"name":"Matthew G. Taylor","order":35,"profile_path":"\/il8bIgN6sANpmMSohJGvpNbeN8A.jpg"},{"cast_id":67,"character":"UN Representative","credit_id":"57e550bcc3a368264b0044c7","id":1239394,"name":"Frank Nakashima","order":36,"profile_path":"\/cY0z7QhmF4bDkzxVCQE5JRLtJKo.jpg"},{"cast_id":69,"character":"UN Representative","credit_id":"57e550f39251411aad0036a8","id":1683938,"name":"Terry Belleville","order":38,"profile_path":null},{"cast_id":70,"character":"UN Representative","credit_id":"57e551bd9251411ab00036e3","id":1683941,"name":"Farzad Sadrian","order":39,"profile_path":null},{"cast_id":71,"character":"UN Representative","credit_id":"57e55212c3a36841e5003b78","id":125579,"name":"Mishu Vellani","order":40,"profile_path":"\/7fp4Jhr9mkLunxTjxdAFKA3QR1A.jpg"},{"cast_id":72,"character":"UN Representative","credit_id":"57e552559251410611004014","id":231140,"name":"Clive Walton","order":41,"profile_path":null},{"cast_id":73,"character":"Young Mako's Father","credit_id":"57e5529ac3a368416500374c","id":1003550,"name":"Peter Kosaka","order":42,"profile_path":null},{"cast_id":74,"character":"Young Mako's Mother","credit_id":"57e552d5c3a368422500341a","id":1683943,"name":"Yiren Stark","order":43,"profile_path":null}],"crew":[{"credit_id":"52fe47a0c3a368484e0d1841","department":"Directing","id":10828,"job":"Director","name":"Guillermo del Toro","profile_path":"\/aBPPwt3jcFw2ridEkKTgchfPaic.jpg"},{"credit_id":"52fe47a0c3a368484e0d1853","department":"Writing","id":114016,"job":"Screenplay","name":"Travis Beacham","profile_path":null},{"credit_id":"52fe47a0c3a368484e0d1885","department":"Writing","id":10828,"job":"Screenplay","name":"Guillermo del Toro","profile_path":"\/aBPPwt3jcFw2ridEkKTgchfPaic.jpg"},{"credit_id":"52fe47a0c3a368484e0d1891","department":"Sound","id":10851,"job":"Original Music Composer","name":"Ramin Djawadi","profile_path":null},{"credit_id":"52fe47a0c3a368484e0d1897","department":"Camera","id":3113,"job":"Director of Photography","name":"Guillermo Navarro","profile_path":"\/AfZkxrEiLlqqHONhfJyVOLrHR8A.jpg"},{"credit_id":"52fe47a0c3a368484e0d189d","department":"Editing","id":10833,"job":"Editor","name":"Peter Amundson","profile_path":null},{"credit_id":"52fe47a0c3a368484e0d18a3","department":"Editing","id":67810,"job":"Editor","name":"John Gilroy","profile_path":null},{"credit_id":"52fe47a0c3a368484e0d18a9","department":"Art","id":6045,"job":"Production Design","name":"Andrew Neskoromny","profile_path":null},{"credit_id":"52fe47a0c3a368484e0d18af","department":"Art","id":8315,"job":"Production Design","name":"Carol Spier","profile_path":null},{"credit_id":"52fe47a0c3a368484e0d18b5","department":"Costume & Make-Up","id":213644,"job":"Costume Design","name":"Kate Hawley","profile_path":null},{"credit_id":"52fe47a0c3a368484e0d18bb","department":"Art","id":957970,"job":"Set Decoration","name":"Peter Nicolakakos","profile_path":null},{"credit_id":"535268260e0a265606002dbc","department":"Writing","id":114016,"job":"Story","name":"Travis Beacham","profile_path":null},{"credit_id":"5352683f0e0a2655fe002f89","department":"Production","id":10828,"job":"Producer","name":"Guillermo del Toro","profile_path":"\/aBPPwt3jcFw2ridEkKTgchfPaic.jpg"},{"credit_id":"535268ae0e0a2655fe002f98","department":"Production","id":61091,"job":"Producer","name":"Jon Jashni","profile_path":null},{"credit_id":"535268c10e0a26560e002f8e","department":"Production","id":114408,"job":"Producer","name":"Mary Parent","profile_path":null},{"credit_id":"535268d20e0a265603003055","department":"Production","id":54211,"job":"Producer","name":"Thomas Tull","profile_path":null},{"credit_id":"535268e30e0a26561100301e","department":"Production","id":19770,"job":"Executive Producer","name":"Callum Greene","profile_path":null},{"credit_id":"53526920c3a3681d9800275d","department":"Production","id":6347,"job":"Casting","name":"Margery Simkin","profile_path":"\/dCyAWZGEaW1OlGgh5ALiqGfsbpb.jpg"},{"credit_id":"53526945c3a3681d98002763","department":"Art","id":1311175,"job":"Art Direction","name":"Andrew Li","profile_path":null},{"credit_id":"570bba48c3a3680fc2007ca5","department":"Art","id":10836,"job":"Supervising Art Director","name":"Elinor Rose Galbraith","profile_path":null},{"credit_id":"570bba2592514113120002d0","department":"Art","id":8285,"job":"Supervising Art Director","name":"Richard L. Johnson","profile_path":null},{"credit_id":"53526972c3a3681d87002897","department":"Art","id":223991,"job":"Art Direction","name":"Sandi Tanaka","profile_path":null},{"credit_id":"553407b4925141529b005aa2","department":"Crew","id":1456696,"job":"Compositors","name":"Brian N. Bentley","profile_path":null},{"credit_id":"553d5a72c3a368784500d1ca","department":"Visual Effects","id":1450362,"job":"Visual Effects","name":"Scott F. Johnston","profile_path":null},{"credit_id":"5548cf8dc3a3687886002388","department":"Visual Effects","id":1460628,"job":"Visual Effects","name":"Weicheng Jiang","profile_path":null},{"credit_id":"5549551392514104cd0007df","department":"Crew","id":1463784,"job":"Digital Effects Supervisor","name":"Yuhon Ng","profile_path":null},{"credit_id":"554fb2989251416984004e78","department":"Crew","id":1447542,"job":"Compositors","name":"Erik Classen","profile_path":null}]},"images":{"backdrops":[{"aspect_ratio":1.7777777777778,"file_path":"\/iB0RsWVoOXzicPi2Yy5xmTYMbho.jpg","height":1080,"iso_639_1":null,"vote_average":5.6140350877193,"vote_count":13,"width":1920},{"aspect_ratio":1.7777777777778,"file_path":"\/bCJLxmgNaZtpMyWKCCiTYrf3YOT.jpg","height":1080,"iso_639_1":"xx","vote_average":5.5476190476191,"vote_count":17,"width":1920},{"aspect_ratio":1.7777777777778,"file_path":"\/jfSzr1QNiAbWHv7B9m4wrbaqSRF.jpg","height":1080,"iso_639_1":null,"vote_average":5.4924983692107,"vote_count":10,"width":1920},{"aspect_ratio":1.7777777777778,"file_path":"\/oGnbZ50nrp5vEVrgPP5RgbqXkPu.jpg","height":1080,"iso_639_1":null,"vote_average":5.3925353925354,"vote_count":11,"width":1920},{"aspect_ratio":1.7777777777778,"file_path":"\/1PoB1xNgK5cqtHkd9ziaYJZM9Bq.jpg","height":1080,"iso_639_1":"en","vote_average":5.3772893772894,"vote_count":2,"width":1920},{"aspect_ratio":1.7777777777778,"file_path":"\/fFrUEivISpDAWaow29ZIs9gS8lN.jpg","height":1080,"iso_639_1":null,"vote_average":5.3174603174603,"vote_count":3,"width":1920},{"aspect_ratio":1.7777777777778,"file_path":"\/sN0xNMjXbfE9TQ1QA8a571VB4zg.jpg","height":1080,"iso_639_1":null,"vote_average":5.312925170068,"vote_count":7,"width":1920},{"aspect_ratio":1.7777777777778,"file_path":"\/ekvcl6uedTtTjuKns4wBnWXU575.jpg","height":1080,"iso_639_1":null,"vote_average":5.3113553113553,"vote_count":2,"width":1920},{"aspect_ratio":1.7777777777778,"file_path":"\/qAeEr6HVW9K1nhv5aSBREOwenUp.jpg","height":1080,"iso_639_1":null,"vote_average":5.2454212454212,"vote_count":2,"width":1920},{"aspect_ratio":1.7777777777778,"file_path":"\/lr6xcnOxG5lidffAfKBRgQeAyAx.jpg","height":1080,"iso_639_1":"xx","vote_average":5.2454212454212,"vote_count":2,"width":1920},{"aspect_ratio":1.7777777777778,"file_path":"\/jhRsL00pT7k2s8UbEijOEXW5p2p.jpg","height":1080,"iso_639_1":null,"vote_average":5.2453102453102,"vote_count":3,"width":1920},{"aspect_ratio":1.7777777777778,"file_path":"\/BokZJv5SNN2y57smMWlQrCzoxR.jpg","height":1080,"iso_639_1":null,"vote_average":5.2380952380952,"vote_count":3,"width":1920},{"aspect_ratio":1.7777777777778,"file_path":"\/w8zniXHXdeLpUEBcmjnES6G499V.jpg","height":1080,"iso_639_1":null,"vote_average":5.2306547619048,"vote_count":1,"width":1920},{"aspect_ratio":1.7777777777778,"file_path":"\/lVexkOcwvaoAW4YgtERsaefj9hx.jpg","height":1080,"iso_639_1":null,"vote_average":5.2232142857143,"vote_count":1,"width":1920},{"aspect_ratio":1.7777777777778,"file_path":"\/2bdXKqYBqyOwNsMLQm0mN79OAAK.jpg","height":1080,"iso_639_1":null,"vote_average":5.2232142857143,"vote_count":1,"width":1920},{"aspect_ratio":1.7777777777778,"file_path":"\/DIbUXvWIEf9hORJT2dvJqVB7eO.jpg","height":1080,"iso_639_1":null,"vote_average":5.2161172161172,"vote_count":2,"width":1920},{"aspect_ratio":1.7777777777778,"file_path":"\/4JRjVn1Kd8nCnfPjf9RgLo6tnVa.jpg","height":1080,"iso_639_1":null,"vote_average":5.2087912087912,"vote_count":2,"width":1920},{"aspect_ratio":1.7777777777778,"file_path":"\/iRKkCz5ei3ky3tVtaPY03rC80C9.jpg","height":1080,"iso_639_1":null,"vote_average":5.2087912087912,"vote_count":2,"width":1920},{"aspect_ratio":1.7777777777778,"file_path":"\/4mqGSPVmWKi4LFZBcA4NIklcjhw.jpg","height":1080,"iso_639_1":null,"vote_average":5.2083333333333,"vote_count":1,"width":1920},{"aspect_ratio":1.7777777777778,"file_path":"\/edUQdEKw7RtaPjqm8zHyPqzEx48.jpg","height":1080,"iso_639_1":null,"vote_average":5.2014652014652,"vote_count":2,"width":1920},{"aspect_ratio":1.7772511848341,"file_path":"\/iTgM00obCSae27acXkybb8s6EIo.jpg","height":1266,"iso_639_1":null,"vote_average":5.2014652014652,"vote_count":2,"width":2250},{"aspect_ratio":1.7777777777778,"file_path":"\/6WQIw40Xe9fdlydUoCiuWVt5P9g.jpg","height":1080,"iso_639_1":null,"vote_average":5.1954513148543,"vote_count":4,"width":1920},{"aspect_ratio":1.7777777777778,"file_path":"\/kWOcqXQdqVlUtGMfgS0uqD8jJKZ.jpg","height":720,"iso_639_1":"xx","vote_average":5.1941391941392,"vote_count":2,"width":1280},{"aspect_ratio":1.7777777777778,"file_path":"\/9THqOM1c94HD6UGoDT83cldwO3l.jpg","height":1080,"iso_639_1":"xx","vote_average":5.1934523809524,"vote_count":1,"width":1920},{"aspect_ratio":1.7777777777778,"file_path":"\/3hd01BFDArxvYF65S6hwmqyfk8t.jpg","height":1080,"iso_639_1":null,"vote_average":5.1868131868132,"vote_count":2,"width":1920},{"aspect_ratio":1.7777777777778,"file_path":"\/a2VHt96YAK6trNIyhWwsjbYSobA.jpg","height":1080,"iso_639_1":null,"vote_average":5.1868131868132,"vote_count":2,"width":1920},{"aspect_ratio":1.7777777777778,"file_path":"\/3PDI6qPDWhO4GDy1n8WM0BG2IeT.jpg","height":1080,"iso_639_1":null,"vote_average":5.1794871794872,"vote_count":2,"width":1920},{"aspect_ratio":1.7777777777778,"file_path":"\/n9KQ8RnYa0K6SFSXtpdOXMYun0Y.jpg","height":1080,"iso_639_1":null,"vote_average":5.1785714285714,"vote_count":1,"width":1920},{"aspect_ratio":1.7777777777778,"file_path":"\/yjwAeHKTzwyZ7q5RAbA3RmVGVk9.jpg","height":1080,"iso_639_1":null,"vote_average":5.1721611721612,"vote_count":2,"width":1920},{"aspect_ratio":1.7777777777778,"file_path":"\/qu4REUtwkPHvmnXrtszI6UDs0wg.jpg","height":1080,"iso_639_1":"xx","vote_average":5.1711309523809,"vote_count":1,"width":1920},{"aspect_ratio":1.7777777777778,"file_path":"\/3I2ZYumeOzyqncWkPg6nAolmzA3.jpg","height":1080,"iso_639_1":null,"vote_average":5.1711309523809,"vote_count":1,"width":1920},{"aspect_ratio":1.7777777777778,"file_path":"\/axhLAqEDE7irpFmchywreYjFYU8.jpg","height":1080,"iso_639_1":"xx","vote_average":5.1062271062271,"vote_count":2,"width":1920},{"aspect_ratio":1.7777777777778,"file_path":"\/gYSEmF72YkjNffTyI5ReqHctmgD.jpg","height":1080,"iso_639_1":null,"vote_average":0,"vote_count":0,"width":1920},{"aspect_ratio":1.7777777777778,"file_path":"\/eiuFK9Mgn6rdSiP8r4P7xXyKkiX.jpg","height":1080,"iso_639_1":"xx","vote_average":0,"vote_count":0,"width":1920},{"aspect_ratio":1.7777777777778,"file_path":"\/sRCVoELHlos9d4Wnhg0ayltG3Xd.jpg","height":1080,"iso_639_1":null,"vote_average":0,"vote_count":0,"width":1920},{"aspect_ratio":1.7777777777778,"file_path":"\/jlIIh7ZtEHVXcLy02CLh7fdQ79K.jpg","height":1080,"iso_639_1":"en","vote_average":0,"vote_count":0,"width":1920},{"aspect_ratio":1.7777777777778,"file_path":"\/tSOzemdMjzdou3GYVFxEdJv0MH8.jpg","height":1080,"iso_639_1":"en","vote_average":0,"vote_count":0,"width":1920},{"aspect_ratio":1.7777777777778,"file_path":"\/x5BHqVmFAWeBIEupdVPU4PCq5bY.jpg","height":1080,"iso_639_1":"en","vote_average":0,"vote_count":0,"width":1920},{"aspect_ratio":1.7777777777778,"file_path":"\/mrvk58M4PLBLglxUaq82thnrRhg.jpg","height":1080,"iso_639_1":"en","vote_average":0,"vote_count":0,"width":1920},{"aspect_ratio":1.7777777777778,"file_path":"\/qrD5QPSnwCt03TyLnSyzbRIlqB7.jpg","height":1080,"iso_639_1":"en","vote_average":0,"vote_count":0,"width":1920},{"aspect_ratio":1.7777777777778,"file_path":"\/hOU6LXrAPSmnKk3tjtr4rkkLpAq.jpg","height":1080,"iso_639_1":null,"vote_average":0,"vote_count":0,"width":1920},{"aspect_ratio":1.7777777777778,"file_path":"\/5tTTioC82qetnuKT4hmFM5wROEu.jpg","height":1080,"iso_639_1":null,"vote_average":0,"vote_count":0,"width":1920},{"aspect_ratio":1.7777777777778,"file_path":"\/rgLRAsabpcZ3PMGv4TCfyC8wJlZ.jpg","height":1080,"iso_639_1":null,"vote_average":0,"vote_count":0,"width":1920},{"aspect_ratio":1.7777777777778,"file_path":"\/kEnYlu6NzMNJjaBjWLPq331kE1j.jpg","height":1080,"iso_639_1":null,"vote_average":0,"vote_count":0,"width":1920},{"aspect_ratio":1.7777777777778,"file_path":"\/yrESeeUOj8ZWd7JyZ0bwDaM4Qti.jpg","height":1080,"iso_639_1":null,"vote_average":0,"vote_count":0,"width":1920},{"aspect_ratio":1.7777777777778,"file_path":"\/fMMACWdIFp0XAtlMHToZGloSZTZ.jpg","height":1080,"iso_639_1":null,"vote_average":0,"vote_count":0,"width":1920},{"aspect_ratio":1.7777777777778,"file_path":"\/jaLGvaZ1lNKeXfOhlMLlHZN4ntB.jpg","height":1080,"iso_639_1":null,"vote_average":0,"vote_count":0,"width":1920},{"aspect_ratio":1.7777777777778,"file_path":"\/3RzBKVK2eQli1W4j8EVnpvf994T.jpg","height":1080,"iso_639_1":"xx","vote_average":0,"vote_count":0,"width":1920},{"aspect_ratio":1.7777777777778,"file_path":"\/rO4y7PRzezIsIVecxxeHv7b7gW1.jpg","height":1080,"iso_639_1":null,"vote_average":0,"vote_count":0,"width":1920}],"posters":[{"aspect_ratio":0.66666666666667,"file_path":"\/sCJEwEShZvruTpQ2a4yiX3Q9EyZ.jpg","height":1500,"iso_639_1":"en","vote_average":5.4986522911051,"vote_count":43,"width":1000},{"aspect_ratio":0.675625,"file_path":"\/oB58xARUcE9WCZ1m2mt5dSDCA4P.jpg","height":1600,"iso_639_1":null,"vote_average":5.3772893772894,"vote_count":2,"width":1081},{"aspect_ratio":0.69970703125,"file_path":"\/kkMCWgna47OEEukZKhztGYccqQz.jpg","height":2048,"iso_639_1":"es","vote_average":5.3699633699634,"vote_count":2,"width":1433},{"aspect_ratio":0.66666666666667,"file_path":"\/xzT2FOoXEFkdI3Himpa0bgUZlCE.jpg","height":1500,"iso_639_1":"en","vote_average":5.3647416413374,"vote_count":31,"width":1000},{"aspect_ratio":0.68119891008174,"file_path":"\/lmz7kSz4bZzva9fMj1upIixTaK4.jpg","height":1468,"iso_639_1":"pt","vote_average":5.3518123667377,"vote_count":4,"width":1000},{"aspect_ratio":0.66666666666667,"file_path":"\/ax2FC8ZBPjGF3Bd0kKrmxoYxERG.jpg","height":1500,"iso_639_1":"fr","vote_average":5.3463203463203,"vote_count":3,"width":1000},{"aspect_ratio":0.70588235294118,"file_path":"\/vhCqtWKxIMI0FCV2Y3proKZ3cXY.jpg","height":850,"iso_639_1":"es","vote_average":5.3463203463203,"vote_count":3,"width":600},{"aspect_ratio":0.66666666666667,"file_path":"\/pSz8Sj2Nl8RgLzYYbPyToaKTeG2.jpg","height":1500,"iso_639_1":"pt","vote_average":5.3125,"vote_count":1,"width":1000},{"aspect_ratio":0.66666666666667,"file_path":"\/eLbU94akOp7g0XoD3U2qcwebuZR.jpg","height":1500,"iso_639_1":"fr","vote_average":5.3125,"vote_count":1,"width":1000},{"aspect_ratio":0.70093457943925,"file_path":"\/5xxqioIyVFMrLuSdpmQL9Enp5Pt.jpg","height":856,"iso_639_1":"zh","vote_average":5.3125,"vote_count":1,"width":600},{"aspect_ratio":0.66666666666667,"file_path":"\/kCYv451CuaQRfTNL5krZwsi2W9i.jpg","height":1500,"iso_639_1":"hu","vote_average":5.3125,"vote_count":1,"width":1000},{"aspect_ratio":0.66666666666667,"file_path":"\/tjYSTX6rwAA5Hzh3KY67Y3PTwJP.jpg","height":1500,"iso_639_1":"hu","vote_average":5.3125,"vote_count":1,"width":1000},{"aspect_ratio":0.675,"file_path":"\/gyUwT4SKvS1Fry6JGsyPNo32RPX.jpg","height":1600,"iso_639_1":"es","vote_average":5.3125,"vote_count":1,"width":1080},{"aspect_ratio":0.66666666666667,"file_path":"\/hLBYD9qEYy8ZpScHJ2FgFpcqkP1.jpg","height":2100,"iso_639_1":"it","vote_average":5.3125,"vote_count":1,"width":1400},{"aspect_ratio":0.66666666666667,"file_path":"\/6vOiriCVzOKYaLKxeQlDkvDDDfb.jpg","height":750,"iso_639_1":"bg","vote_average":5.3125,"vote_count":1,"width":500},{"aspect_ratio":0.706,"file_path":"\/azGdrOH2YjABV2I1XIwhu3LcLCA.jpg","height":1000,"iso_639_1":"bg","vote_average":5.3125,"vote_count":1,"width":706},{"aspect_ratio":0.7,"file_path":"\/A9YmwtXmdlsB0Hp70TImNS4svOy.jpg","height":1500,"iso_639_1":"it","vote_average":5.3125,"vote_count":1,"width":1050},{"aspect_ratio":0.66666666666667,"file_path":"\/x0jh4XBpMwnPYH1eEyq6QYauq4Q.jpg","height":2100,"iso_639_1":"de","vote_average":5.3125,"vote_count":1,"width":1400},{"aspect_ratio":0.67435728411338,"file_path":"\/qixhZBP9uSWx0LEXZCxjq4VL9BK.jpg","height":1517,"iso_639_1":"ja","vote_average":5.3125,"vote_count":1,"width":1023},{"aspect_ratio":0.69344262295082,"file_path":"\/n74KvyNJtc5zaQBsGs6V5H60n7h.jpg","height":1220,"iso_639_1":"el","vote_average":5.312,"vote_count":1,"width":846},{"aspect_ratio":0.70666666666667,"file_path":"\/xe7s6ZonvdlREcyVqCuiJhy65YM.jpg","height":750,"iso_639_1":"hu","vote_average":5.2752976190476,"vote_count":1,"width":530},{"aspect_ratio":0.66666666666667,"file_path":"\/rEsGsJV0zHpC4XwhIZPRsPGIUNC.jpg","height":3000,"iso_639_1":"zh","vote_average":5.2678571428571,"vote_count":1,"width":2000},{"aspect_ratio":0.66666666666667,"file_path":"\/vtOFRlWmnGnCbJRpIABTuDuMDUu.jpg","height":3000,"iso_639_1":"zh","vote_average":5.2678571428571,"vote_count":1,"width":2000},{"aspect_ratio":0.71083333333333,"file_path":"\/8REoDtTpVAIvYUKt4Tcw1RD3TYQ.jpg","height":1200,"iso_639_1":"cs","vote_average":5.2678571428571,"vote_count":1,"width":853},{"aspect_ratio":0.676875,"file_path":"\/tTTz7Jg4ZEdyk1A5XMCmjmSpn5N.jpg","height":1600,"iso_639_1":"es","vote_average":5.2678571428571,"vote_count":1,"width":1083},{"aspect_ratio":0.71083333333333,"file_path":"\/q4Wz2rm72irFS96gQ1CKRZ1GxnW.jpg","height":1200,"iso_639_1":"cs","vote_average":5.2529761904762,"vote_count":1,"width":853},{"aspect_ratio":0.6775,"file_path":"\/ohXylhI6c5WMahrKIsqESXC2clP.jpg","height":1600,"iso_639_1":"es","vote_average":5.2529761904762,"vote_count":1,"width":1084},{"aspect_ratio":0.66225165562914,"file_path":"\/vbizdc5DGSLllTKfNJxlfwgMByQ.jpg","height":755,"iso_639_1":"es","vote_average":5.2455357142857,"vote_count":1,"width":500},{"aspect_ratio":0.675,"file_path":"\/ya2CZRawER7x7XL69EWooM5uUov.jpg","height":800,"iso_639_1":"es","vote_average":5.2455357142857,"vote_count":1,"width":540},{"aspect_ratio":0.70666666666667,"file_path":"\/bmckTHfJ92BnRhviyw8xK1xA7jW.jpg","height":750,"iso_639_1":"hu","vote_average":5.2454212454212,"vote_count":2,"width":530},{"aspect_ratio":0.75,"file_path":"\/cqpAEMzclFdWa9hWDFCqgczuyVr.jpg","height":1500,"iso_639_1":"fr","vote_average":5.2454212454212,"vote_count":2,"width":1125},{"aspect_ratio":0.75,"file_path":"\/u1xJ23vfKUxZIHua5cT3DC1RDvo.jpg","height":1024,"iso_639_1":"fr","vote_average":5.2454212454212,"vote_count":2,"width":768},{"aspect_ratio":0.75,"file_path":"\/yw96zYSkBDcRBx32yZ80dBB3XeX.jpg","height":1600,"iso_639_1":"fr","vote_average":5.2454212454212,"vote_count":2,"width":1200},{"aspect_ratio":0.7125,"file_path":"\/cUHQmQtrQ8hRikjaxLdB3zbvqjV.jpg","height":800,"iso_639_1":"xx","vote_average":5.2380952380952,"vote_count":1,"width":570},{"aspect_ratio":0.7,"file_path":"\/i4mwdjqRYtbZOVJ6rEpMCAUvX5C.jpg","height":800,"iso_639_1":"xx","vote_average":5.1934523809524,"vote_count":1,"width":560},{"aspect_ratio":0.69324090121317,"file_path":"\/h3T4JAvDhnJK2MqSHy4TMx55rbZ.jpg","height":1154,"iso_639_1":"hu","vote_average":5.1860119047619,"vote_count":1,"width":800},{"aspect_ratio":0.66666666666667,"file_path":"\/nSv1kxoXQVNZcgOLGs82C01vw5.jpg","height":1500,"iso_639_1":"en","vote_average":5.1817716333845,"vote_count":30,"width":1000},{"aspect_ratio":0.66666666666667,"file_path":"\/gHnKVBdzOThKCdtIl7MSzUgwkPX.jpg","height":2100,"iso_639_1":"en","vote_average":5.1803751803752,"vote_count":3,"width":1400},{"aspect_ratio":0.66666666666667,"file_path":"\/dJk5Rc3JyOOulSJxGys7XQbjQX1.jpg","height":1500,"iso_639_1":"en","vote_average":5.1803751803752,"vote_count":3,"width":1000},{"aspect_ratio":0.75,"file_path":"\/4REUE6LYwgYsXtXurlQ87sQ4GV5.jpg","height":1500,"iso_639_1":"en","vote_average":5.1711309523809,"vote_count":1,"width":1125},{"aspect_ratio":0.6640625,"file_path":"\/ocfV1LLJvzEghwbWfn5tReo2ec4.jpg","height":1280,"iso_639_1":"en","vote_average":5.1711309523809,"vote_count":1,"width":850},{"aspect_ratio":0.66666666666667,"file_path":"\/7VqgYyZi953rqi3zq89L3Gi1i5u.jpg","height":1500,"iso_639_1":"en","vote_average":5.1374916163649,"vote_count":8,"width":1000},{"aspect_ratio":0.66666666666667,"file_path":"\/68zfp76MM64c2kiDY7hoygH39RR.jpg","height":1500,"iso_639_1":"en","vote_average":5.1224489795918,"vote_count":7,"width":1000},{"aspect_ratio":0.66666666666667,"file_path":"\/jz0YTjCZycusc41m4wkqry3ykkK.jpg","height":2100,"iso_639_1":"en","vote_average":5.1172707889126,"vote_count":4,"width":1400},{"aspect_ratio":0.66666666666667,"file_path":"\/423LFBzj3TNvFZnK43EKW5xTfxg.jpg","height":1500,"iso_639_1":"en","vote_average":5.1158301158301,"vote_count":11,"width":1000},{"aspect_ratio":0.66666666666667,"file_path":"\/mddDecdPCi9jHNCPOzHVE5isuK3.jpg","height":1500,"iso_639_1":"en","vote_average":5.1062271062271,"vote_count":2,"width":1000},{"aspect_ratio":0.66666666666667,"file_path":"\/2BmSWRb0rvaChMp3c4E61QQihP9.jpg","height":1500,"iso_639_1":"en","vote_average":5.1062271062271,"vote_count":2,"width":1000},{"aspect_ratio":0.66666666666667,"file_path":"\/q0d0JVfrvr8MFCEZpITdGUl13X9.jpg","height":1500,"iso_639_1":"en","vote_average":5.1062271062271,"vote_count":2,"width":1000},{"aspect_ratio":0.66666666666667,"file_path":"\/38eggvDaCybE8RWqD2WRSMX9RYm.jpg","height":1500,"iso_639_1":"en","vote_average":5.1062271062271,"vote_count":2,"width":1000},{"aspect_ratio":0.66666666666667,"file_path":"\/utSgnJ6gn6KHQTzuc8b5oidI1Gk.jpg","height":1500,"iso_639_1":"en","vote_average":5.1062271062271,"vote_count":2,"width":1000},{"aspect_ratio":0.66666666666667,"file_path":"\/hJqe0JYzxocEVY38D3mzpvaCGAt.jpg","height":1500,"iso_639_1":"en","vote_average":5.1047619047619,"vote_count":12,"width":1000},{"aspect_ratio":0.66666666666667,"file_path":"\/aP1GB8yCYLfztyaqjzOuHZAGr55.jpg","height":1500,"iso_639_1":"en","vote_average":5.1035196687371,"vote_count":29,"width":1000},{"aspect_ratio":0.66666666666667,"file_path":"\/su86QRCOzPdm9tOAubiWVyn38lK.jpg","height":1500,"iso_639_1":"en","vote_average":5.1030561478323,"vote_count":4,"width":1000},{"aspect_ratio":0.66666666666667,"file_path":"\/et6OUJE5KAaykJmP5HFkUZfq9Ko.jpg","height":1701,"iso_639_1":"en","vote_average":5.1020408163265,"vote_count":7,"width":1134},{"aspect_ratio":0.66666666666667,"file_path":"\/gMv3ZKX2qJW4oqBAYxfOKE8nc7t.jpg","height":1500,"iso_639_1":"en","vote_average":5.0854700854701,"vote_count":15,"width":1000},{"aspect_ratio":0.66666666666667,"file_path":"\/mMiQ5WcFq5KbUaZqCFAL6zgBPiB.jpg","height":1500,"iso_639_1":"en","vote_average":5.0770308123249,"vote_count":5,"width":1000},{"aspect_ratio":0.66666666666667,"file_path":"\/mAx7F1uq3eZLIgFduDan26CYsSA.jpg","height":1500,"iso_639_1":"en","vote_average":5.010060362173,"vote_count":8,"width":1000},{"aspect_ratio":0.66666666666667,"file_path":"\/1rp9takFPpn9QnJVgfGE9UsPghD.jpg","height":2100,"iso_639_1":"en","vote_average":5.0062656641604,"vote_count":13,"width":1400},{"aspect_ratio":0.67340067340067,"file_path":"\/g6712mK7A2seDAbVGGewViZKyVC.jpg","height":891,"iso_639_1":"en","vote_average":4.9832327297116,"vote_count":8,"width":600},{"aspect_ratio":0.66666666666667,"file_path":"\/scmmz63RgdeOtJKXaG4y7xzNocK.jpg","height":2400,"iso_639_1":"en","vote_average":4.9765258215962,"vote_count":8,"width":1600},{"aspect_ratio":0.69348127600555,"file_path":"\/hHVIyoBUkIjuInBhD9xZGQNWurV.jpg","height":1442,"iso_639_1":"en","vote_average":4.975845410628,"vote_count":6,"width":1000},{"aspect_ratio":0.67340067340067,"file_path":"\/ikRCF3xyUvvKdnrNhkDFTPY2epX.jpg","height":891,"iso_639_1":"en","vote_average":4.9751243781094,"vote_count":4,"width":600},{"aspect_ratio":0.67624683009298,"file_path":"\/t0Wo87iGuODF4JbFlDuIAwfd4VC.jpg","height":1183,"iso_639_1":"en","vote_average":4.9641226353555,"vote_count":10,"width":800},{"aspect_ratio":0.684,"file_path":"\/6oCZHgNNv76lHbk2bSKJYxy6KNW.jpg","height":1500,"iso_639_1":"en","vote_average":4.9344375431332,"vote_count":6,"width":1026},{"aspect_ratio":0.72593167701863,"file_path":"\/UboyTCTjNLUv9J4KpzJMmjLWiJ.jpg","height":1288,"iso_639_1":"en","vote_average":4.9292149292149,"vote_count":11,"width":935},{"aspect_ratio":0.67340067340067,"file_path":"\/zljsifrWOVPnfnNEwvVvotH4jlg.jpg","height":891,"iso_639_1":"en","vote_average":4.9159663865546,"vote_count":5,"width":600},{"aspect_ratio":0.67340067340067,"file_path":"\/kzJivq4M1aoK2v1RNRUZwmZHnx0.jpg","height":891,"iso_639_1":"en","vote_average":4.9159663865546,"vote_count":5,"width":600},{"aspect_ratio":0.67340067340067,"file_path":"\/lEaMV699WUhDB8Zq74ifiWQRWP1.jpg","height":891,"iso_639_1":"en","vote_average":4.9159663865546,"vote_count":5,"width":600},{"aspect_ratio":0.66666666666667,"file_path":"\/gP5QWAntxa2uvrMBPc3T5MrUV4w.jpg","height":2400,"iso_639_1":"ko","vote_average":0,"vote_count":0,"width":1600},{"aspect_ratio":0.66666666666667,"file_path":"\/341j0JT9h9gJVL5ZPVP75z4pg5e.jpg","height":1500,"iso_639_1":"ko","vote_average":0,"vote_count":0,"width":1000},{"aspect_ratio":0.66666666666667,"file_path":"\/4cO9ABl9D7ert255zRJWQBuObkw.jpg","height":3000,"iso_639_1":"no","vote_average":0,"vote_count":0,"width":2000},{"aspect_ratio":0.7,"file_path":"\/vT3GDQkC9n9t0zUcUAFJ4gN0gO0.jpg","height":2000,"iso_639_1":"it","vote_average":0,"vote_count":0,"width":1400},{"aspect_ratio":0.7,"file_path":"\/iXz30HrGXBtvjT6sHD5nyYyAG4y.jpg","height":2000,"iso_639_1":"it","vote_average":0,"vote_count":0,"width":1400},{"aspect_ratio":0.66666666666667,"file_path":"\/bQVcoeDt2E7tijIQnGeYZfXFqLU.jpg","height":1500,"iso_639_1":"fr","vote_average":0,"vote_count":0,"width":1000},{"aspect_ratio":0.69989224137931,"file_path":"\/zlaggpm8jK4y8yBzjliHclriZNv.jpg","height":1856,"iso_639_1":"zh","vote_average":0,"vote_count":0,"width":1299},{"aspect_ratio":0.7,"file_path":"\/1UkuA7AAHk86kB2U3OdNlDwv8uR.jpg","height":1000,"iso_639_1":"zh","vote_average":0,"vote_count":0,"width":700},{"aspect_ratio":0.69989224137931,"file_path":"\/3JYjxSw5K2nuYmLZa60rLiVAJhk.jpg","height":1856,"iso_639_1":"zh","vote_average":0,"vote_count":0,"width":1299},{"aspect_ratio":0.69951534733441,"file_path":"\/nNwr1ar4gAhTbmIEGux9SSxSycc.jpg","height":1857,"iso_639_1":"zh","vote_average":0,"vote_count":0,"width":1299},{"aspect_ratio":0.68634179821551,"file_path":"\/7YgrnZ5opCgV3wa165CJp5FdrI7.jpg","height":1457,"iso_639_1":"zh","vote_average":0,"vote_count":0,"width":1000},{"aspect_ratio":0.69444444444444,"file_path":"\/994JDuUV5hqlsiSNF5j7rqFAydK.jpg","height":1368,"iso_639_1":"he","vote_average":0,"vote_count":0,"width":950},{"aspect_ratio":0.6671686746988,"file_path":"\/qlXKC8lJEMWv56Mh3tRV1PF8hdi.jpg","height":1328,"iso_639_1":"uk","vote_average":0,"vote_count":0,"width":886},{"aspect_ratio":0.66666666666667,"file_path":"\/vIk5zGMraMosP3bpMtdEwXNGatU.jpg","height":2100,"iso_639_1":"da","vote_average":0,"vote_count":0,"width":1400},{"aspect_ratio":0.67733990147783,"file_path":"\/mNukCJUKdCsigDR53AraiIYFq0R.jpg","height":812,"iso_639_1":"th","vote_average":0,"vote_count":0,"width":550},{"aspect_ratio":0.66666666666667,"file_path":"\/lpB88EinXXsoqbuteJVT5XVUPx6.jpg","height":1902,"iso_639_1":"sk","vote_average":0,"vote_count":0,"width":1268},{"aspect_ratio":0.683,"file_path":"\/eEQkIXhSVnnM3Iv1Fhc3irfLmZu.jpg","height":1000,"iso_639_1":"ru","vote_average":0,"vote_count":0,"width":683},{"aspect_ratio":0.69333333333333,"file_path":"\/j0bZeFRfnKnAbJLsAV7DufpEEZI.jpg","height":1500,"iso_639_1":"pt","vote_average":0,"vote_count":0,"width":1040},{"aspect_ratio":0.683,"file_path":"\/9m13NAV2iJkDQgovcoj8sMFKkJG.jpg","height":1000,"iso_639_1":"ru","vote_average":0,"vote_count":0,"width":683},{"aspect_ratio":0.67726161369193,"file_path":"\/8lW8ChFxctBLg6PhWuYNNzlQKso.jpg","height":818,"iso_639_1":null,"vote_average":0,"vote_count":0,"width":554},{"aspect_ratio":0.74981103552532,"file_path":"\/cshzeMgg3CNxBRsl27j9xmqL0dG.jpg","height":1323,"iso_639_1":null,"vote_average":0,"vote_count":0,"width":992},{"aspect_ratio":0.77464788732394,"file_path":"\/gxpZ3l8keihj6bqvAkGCHK8WBvf.jpg","height":1633,"iso_639_1":null,"vote_average":0,"vote_count":0,"width":1265},{"aspect_ratio":0.70126227208976,"file_path":"\/i221huKNA2RXIyMXPPaIW8VlfvT.jpg","height":1426,"iso_639_1":null,"vote_average":0,"vote_count":0,"width":1000},{"aspect_ratio":0.70126227208976,"file_path":"\/wazfegz8WHExv0FLCNbsGy049eS.jpg","height":1426,"iso_639_1":null,"vote_average":0,"vote_count":0,"width":1000},{"aspect_ratio":0.70126227208976,"file_path":"\/jEQhQrM1lKZljMxbn4g0tkgt71C.jpg","height":1426,"iso_639_1":null,"vote_average":0,"vote_count":0,"width":1000},{"aspect_ratio":0.70126227208976,"file_path":"\/4lNuXR7Li8OYBYG5K2RLXJ4pXLF.jpg","height":1426,"iso_639_1":null,"vote_average":0,"vote_count":0,"width":1000},{"aspect_ratio":0.70126227208976,"file_path":"\/cPRZcSKiK1kZvfVAZWgmDnsWdky.jpg","height":1426,"iso_639_1":null,"vote_average":0,"vote_count":0,"width":1000},{"aspect_ratio":0.70126227208976,"file_path":"\/kVeMjyrmGO060gcj1EYJ55omhzK.jpg","height":1426,"iso_639_1":null,"vote_average":0,"vote_count":0,"width":1000},{"aspect_ratio":0.70126227208976,"file_path":"\/8fz3ZCkYDYqn9qR1X7GrWsyXaUe.jpg","height":1426,"iso_639_1":null,"vote_average":0,"vote_count":0,"width":1000},{"aspect_ratio":0.70126227208976,"file_path":"\/9GjaQJ6PN5w9WGOuHTCBzqJgj7L.jpg","height":1426,"iso_639_1":null,"vote_average":0,"vote_count":0,"width":1000},{"aspect_ratio":0.67875,"file_path":"\/3iEayDysQME9QHDFQhGqhk16dqd.jpg","height":1600,"iso_639_1":"es","vote_average":0,"vote_count":0,"width":1086},{"aspect_ratio":0.66666666666667,"file_path":"\/j1O5xh6mZTFJ1naVE6zXAwvqlD9.jpg","height":1200,"iso_639_1":"ru","vote_average":0,"vote_count":0,"width":800},{"aspect_ratio":0.6975,"file_path":"\/14NKfDZ2Uok92SogTz29VjeyJVu.jpg","height":4000,"iso_639_1":null,"vote_average":0,"vote_count":0,"width":2790},{"aspect_ratio":0.67875,"file_path":"\/wtHD5ao9oFfKcOgh86gUXQ6jtlq.jpg","height":1600,"iso_639_1":"es","vote_average":0,"vote_count":0,"width":1086},{"aspect_ratio":0.70733041575492,"file_path":"\/dKX3JLpvxEbVRzYb02RIl9JKQkH.jpg","height":1828,"iso_639_1":"ro","vote_average":0,"vote_count":0,"width":1293},{"aspect_ratio":0.687,"file_path":"\/lN6o91zCLcBXjNniBhTKnJILW4o.jpg","height":5000,"iso_639_1":null,"vote_average":0,"vote_count":0,"width":3435},{"aspect_ratio":0.7,"file_path":"\/4dSPnNTGxvaPnCS2mQFMW8139ui.jpg","height":960,"iso_639_1":"it","vote_average":0,"vote_count":0,"width":672}]}}