{"adult":false,"backdrop_path":"\/jOHyJOF1BWJjR6eOwYfNxYIEkSw.jpg","belongs_to_collection":null,"budget":7100000,"genres":[{"id":80,"name":"Crime"},{"id":18,"name":"Drama"},{"id":53,"name":"Thriller"}],"homepage":"","id":165904,"imdb_id":"tt2377938","original_language":"hi","original_title":"Special Chabbis","overview":"Based on a real life group of con artists who pulled off clever robberies during 1980s. This group robbed famous businessmen and politicians by impersonating the CBI or Income tax officers and conducting raids.","popularity":0.011016,"poster_path":"\/9Kc9npOD0oiuKaT2GAmJsAC8S6A.jpg","production_companies":[{"name":"Viacom 18 Motion Pictures","id":7356}],"production_countries":[{"iso_3166_1":"IN","name":"India"}],"release_date":"2013-02-07","revenue":18000000,"runtime":144,"spoken_languages":[{"iso_639_1":"hi","name":"\u0939\u093f\u0928\u094d\u0926\u0940"}],"status":"Released","tagline":"Real is Fake & Fake is Real","title":"Special 26","video":false,"vote_average":6.5,"vote_count":20,"credits":{"cast":[{"cast_id":2,"character":"Ajay Singh","credit_id":"52fe4c93c3a36847f8234e25","id":35070,"name":"Akshay Kumar","order":0,"profile_path":"\/4ZxH4Doh9mRv4GOhV0g76skvG0d.jpg"},{"cast_id":3,"character":"Senior Inspector Ranvir Singh","credit_id":"52fe4c93c3a36847f8234e29","id":35792,"name":"Jimmy Shergill","order":1,"profile_path":"\/lQDAT2RzgsZBGeL0qJYgVDBINAL.jpg"},{"cast_id":4,"character":"CBI Officer Wasim Khan","credit_id":"52fe4c93c3a36847f8234e2d","id":35782,"name":"Manoj Bajpayee","order":2,"profile_path":"\/7ueoUJ9r6fIyTP54mOk8hj7tx1I.jpg"},{"cast_id":5,"character":"P.K Sharma (Sharmaji)","credit_id":"52fe4c93c3a36847f8234e31","id":6217,"name":"Anupam Kher","order":3,"profile_path":"\/a58ePX45hBpzDANzdki86Ny9VFu.jpg"},{"cast_id":7,"character":"Priya Chavan","credit_id":"52fe4c93c3a36847f8234e3b","id":113809,"name":"Kajal Agarwal","order":4,"profile_path":"\/bXLXNpmaachLrWW1SrQZITt9e4N.jpg"},{"cast_id":14,"character":"Dancer in song","credit_id":"55d1223e92514131a5008525","id":77239,"name":"Neeru Bajwa","order":5,"profile_path":"\/vbTPmtu4i1jesF67JXhB09AHkuS.jpg"},{"cast_id":17,"character":"Iqbal","credit_id":"57a8edfbc3a368365a0094bc","id":101825,"name":"Kishore Kadam","order":6,"profile_path":"\/nilPF37Dl9VusQ3733nhW3XsGag.jpg"},{"cast_id":22,"character":"Shanti Ji","credit_id":"57a8fbc8c3a368274b008c9d","id":35778,"name":"Divya Dutta","order":7,"profile_path":"\/n3yWF0XMtt5uiiZyThGFQVaMzDk.jpg"},{"cast_id":23,"character":"Joginder","credit_id":"57a8fc029251417659009429","id":648087,"name":"Rajesh Sharma","order":8,"profile_path":"\/kcKqi24pdLO51rJRwNnD3ZUA16x.jpg"},{"cast_id":16,"character":"Solanki","credit_id":"57a8ecfbc3a36826e9008e06","id":110712,"name":"Ujjwal Chopra","order":9,"profile_path":"\/8uHC4efqlKJWUumZxCSoDTV2crA.jpg"},{"cast_id":18,"character":"Sanjay More","credit_id":"57a8eff3c3a36826e9008f14","id":1469937,"name":"Bhagwan Tiwari","order":10,"profile_path":"\/zRfVY3sS9ubLzWQo6io243R0rph.jpg"},{"cast_id":19,"character":"Magandas","credit_id":"57a8f04bc3a368234c009c4f","id":86228,"name":"Tiku Talsania","order":11,"profile_path":"\/nZr6vfBJvHdrfEpwJ2EgKdsk5a8.jpg"},{"cast_id":20,"character":"Telephone Technician","credit_id":"57a8f097c3a368274b00888f","id":86027,"name":"Gurpal Singh","order":12,"profile_path":"\/imPVBjAApRp3uiyttfm7MR9b4rT.jpg"},{"cast_id":21,"character":"Rajeev Gupte","credit_id":"57a8f43dc3a36835f60089ef","id":1663401,"name":"Vikas Shrivastav","order":13,"profile_path":"\/x9OX9eYMYjcOSflT06m5GbiZEGu.jpg"},{"cast_id":24,"character":"Minister's PA","credit_id":"57a8fc8a9251415cfb00a36f","id":1637729,"name":"Mukesh Bhatt","order":14,"profile_path":"\/v51pdYbUelTyXHYfOXkac0A5w1s.jpg"}],"crew":[{"credit_id":"52fe4c93c3a36847f8234e21","department":"Directing","id":123219,"job":"Director","name":"Neeraj Pandey","profile_path":"\/zXhvvETk59D38NQUtcBpR4vUsLh.jpg"},{"credit_id":"52fe4c93c3a36847f8234e41","department":"Editing","id":123225,"job":"Editor","name":"Shree Narayan Singh","profile_path":null},{"credit_id":"52fe4c93c3a36847f8234e47","department":"Production","id":115235,"job":"Producer","name":"Kumar Mangat","profile_path":null},{"credit_id":"52fe4c93c3a36847f8234e4d","department":"Writing","id":123219,"job":"Writer","name":"Neeraj Pandey","profile_path":"\/zXhvvETk59D38NQUtcBpR4vUsLh.jpg"},{"credit_id":"537ef30cc3a36805a800283b","department":"Sound","id":225318,"job":"Music","name":"M.M. Keeravaani","profile_path":"\/aF6fpS2hAVKmm5tqjZavFrlpTSq.jpg"},{"credit_id":"537ef343c3a36805a1002875","department":"Sound","id":1323057,"job":"Music","name":"Surender Sodhi","profile_path":null},{"credit_id":"537ef362c3a3680592002910","department":"Sound","id":88593,"job":"Original Music Composer","name":"Himesh Reshammiya","profile_path":"\/4mNVTiNkryXuGAmg5nG8K4y9m5q.jpg"}]},"images":{"backdrops":[{"aspect_ratio":1.7777777777778,"file_path":"\/jOHyJOF1BWJjR6eOwYfNxYIEkSw.jpg","height":1080,"iso_639_1":null,"vote_average":5.3125,"vote_count":1,"width":1920},{"aspect_ratio":1.7777777777778,"file_path":"\/4uCjYXV7kzwiON1fBsguLvqCIUu.jpg","height":1080,"iso_639_1":null,"vote_average":0,"vote_count":0,"width":1920},{"aspect_ratio":1.7777777777778,"file_path":"\/avsg6vfHi6rpbDE3gVfEoG8Ofi9.jpg","height":1080,"iso_639_1":null,"vote_average":0,"vote_count":0,"width":1920},{"aspect_ratio":1.7777777777778,"file_path":"\/rmrEgJOUoyMkAD77UsZLilTdpKv.jpg","height":1080,"iso_639_1":null,"vote_average":0,"vote_count":0,"width":1920}],"posters":[{"aspect_ratio":0.69220119981541,"file_path":"\/9Kc9npOD0oiuKaT2GAmJsAC8S6A.jpg","height":2167,"iso_639_1":null,"vote_average":5.3772893772894,"vote_count":2,"width":1500},{"aspect_ratio":0.6767578125,"file_path":"\/tZQsQG9TlgdXHHUqw9brgQ0Vekz.jpg","height":1024,"iso_639_1":null,"vote_average":0,"vote_count":0,"width":693}]}}