{"adult":false,"backdrop_path":"\/iO4fslQ9CenAOcg3JfhN6o9va2.jpg","belongs_to_collection":null,"budget":66000000,"genres":[{"id":18,"name":"Drama"},{"id":10752,"name":"War"}],"homepage":"http:\/\/www.warhorsemovie.com\/","id":57212,"imdb_id":"tt1568911","original_language":"en","original_title":"War Horse","overview":"Follows a young man named Albert and his horse, Joey, and how their bond is broken when Joey is sold to the cavalry and sent to the trenches of World War One. Despite being too young to enlist, Albert heads to France to save his friend.","popularity":2.171445,"poster_path":"\/6wMoQyJddEiLCzLUHiX7LNWhDol.jpg","production_companies":[{"name":"DreamWorks SKG","id":27},{"name":"Amblin Entertainment","id":56},{"name":"Reliance Entertainment","id":7294},{"name":"Kennedy\/Marshall Company, The","id":7383}],"production_countries":[{"iso_3166_1":"US","name":"United States of America"}],"release_date":"2011-12-25","revenue":177584879,"runtime":146,"spoken_languages":[{"iso_639_1":"en","name":"English"}],"status":"Released","tagline":"Separated by War. Tested by Battle. Bound by Friendship.","title":"War Horse","video":false,"vote_average":6.9,"vote_count":581,"credits":{"cast":[{"cast_id":2,"character":"Capt. James Nicholls","credit_id":"52fe4928c3a36847f818c121","id":91606,"name":"Tom Hiddleston","order":0,"profile_path":"\/qB1lHPFBPIzw6I7EvsciZ5wyUNS.jpg"},{"cast_id":3,"character":"Maj. Jamie Stewart","credit_id":"52fe4928c3a36847f818c125","id":71580,"name":"Benedict Cumberbatch","order":1,"profile_path":"\/2NQH6clGUjJmVSOjWiVD54gurKE.jpg"},{"cast_id":4,"character":"Geordie Soldier","credit_id":"52fe4928c3a36847f818c129","id":20286,"name":"Toby Kebbell","order":2,"profile_path":"\/wQU3uFk2TWjT2qfs2Z6rkdbWbjx.jpg"},{"cast_id":5,"character":"Rose Narracott","credit_id":"52fe4928c3a36847f818c12d","id":1639,"name":"Emily Watson","order":3,"profile_path":"\/eZ4848eb8ZKSqffosefUrDfFm06.jpg"},{"cast_id":6,"character":"Albert Narracott","credit_id":"52fe4928c3a36847f818c131","id":225692,"name":"Jeremy Irvine","order":4,"profile_path":"\/cNSKuWcb8wdFHsr7tygtEq77s7G.jpg"},{"cast_id":9,"character":"Lyons","credit_id":"52fe4928c3a36847f818c13f","id":11207,"name":"David Thewlis","order":6,"profile_path":"\/1YhN379UKCPt94nbLzncsDHTC9T.jpg"},{"cast_id":16,"character":"Ted Narracott","credit_id":"52fe4929c3a36847f818c161","id":3064,"name":"Peter Mullan","order":7,"profile_path":"\/g344UcfsoYtz3Lt148mDtuQ9CQ0.jpg"},{"cast_id":17,"character":"Pvt. G\u00fcnther Schr\u00f6der","credit_id":"52fe4929c3a36847f818c165","id":5847,"name":"David Kross","order":8,"profile_path":"\/50BcSbOZtfCktGMEepExob45O2h.jpg"},{"cast_id":19,"character":"Friedrich","credit_id":"52fe4929c3a36847f818c16f","id":15086,"name":"Nicolas Bro","order":9,"profile_path":"\/bPfMDMjbFZzelnZQfLzVTk6qlwi.jpg"},{"cast_id":21,"character":"Sgt. Fry","credit_id":"52fe4929c3a36847f818c177","id":1665,"name":"Eddie Marsan","order":11,"profile_path":"\/zcJ2W9BuiBPohtOkPFcYuFfCzji.jpg"},{"cast_id":62,"character":"Emilie","credit_id":"5475a3bac3a36859b9001536","id":1389549,"name":"Celine Buckens","order":12,"profile_path":"\/4g8tU91I2Nba1RnWRpnKPM3f3Zz.jpg"},{"cast_id":64,"character":"Andrew Easton","credit_id":"5475a580925141407a00158f","id":1252495,"name":"Matt Milne","order":14,"profile_path":null},{"cast_id":65,"character":"David Lyons","credit_id":"5475a59f925141527300212b","id":589652,"name":"Robert Emms","order":15,"profile_path":"\/4wdONknsZLWHpH2NSyk0FyPPO8A.jpg"},{"cast_id":66,"character":"Brandt","credit_id":"5475a606925141527300213f","id":65054,"name":"Rainer Bock","order":16,"profile_path":"\/ebmPZimivfRFKYnKp2ygazkJO9r.jpg"},{"cast_id":67,"character":"Sgt. Sam Perkins","credit_id":"5475a64cc3a3687fd9000e79","id":6969,"name":"Geoff Bell","order":17,"profile_path":"\/1zWgEcKr25XSfHGuXdCuFLUvEoX.jpg"},{"cast_id":68,"character":"Sgt. Martin","credit_id":"5475a688c3a368364c0025dd","id":1229255,"name":"Tony Pitts","order":18,"profile_path":null},{"cast_id":69,"character":"Sgt. Maj. Singh","credit_id":"5475a6a49251414f190005df","id":1389553,"name":"Irfan Hussein","order":19,"profile_path":null},{"cast_id":70,"character":"Maj. Tompkins","credit_id":"5475a6bd925141407a0015ca","id":36666,"name":"Pip Torrens","order":20,"profile_path":"\/oufazs9fACQgocDos8vEY5IW1Wr.jpg"},{"cast_id":71,"character":"Lt.Waverley","credit_id":"54cd7459c3a3681c9c000276","id":1225859,"name":"Patrick Kennedy","order":21,"profile_path":"\/zpSuumaMPPr4fGjaoWNUqAsJTeu.jpg"},{"cast_id":73,"character":"","credit_id":"56e1a081c3a3680a260030ef","id":8206,"name":"Hinnerk Sch\u00f6nemann","order":22,"profile_path":"\/w8R9m7GTYnSWsGKb7WA8T3SJv8X.jpg"},{"cast_id":74,"character":"Army Doctor","credit_id":"56e1a0d4c3a3680a260030fc","id":15498,"name":"Liam Cunningham","order":23,"profile_path":"\/8RMX0M8AEaldVAC6WUJIViUdDkm.jpg"},{"cast_id":75,"character":"Soldier","credit_id":"56e1a0e8c3a3680a26003100","id":8206,"name":"Hinnerk Sch\u00f6nemann","order":24,"profile_path":"\/w8R9m7GTYnSWsGKb7WA8T3SJv8X.jpg"},{"cast_id":76,"character":"German Officer at Farm","credit_id":"56e1a110925141088f002b8e","id":550554,"name":"Sebastian H\u00fclk","order":25,"profile_path":"\/1lgRo298X6MZMzf2cWKuELXE74T.jpg"},{"cast_id":77,"character":"French Auctioneer","credit_id":"56e1a13c925141087c002d38","id":5444,"name":"Philippe Nahon","order":26,"profile_path":"\/1ZrnApxh9qZz1EdEB1vKWwoFd5B.jpg"},{"cast_id":78,"character":"German Trench Soldier","credit_id":"56e1a16cc3a3680a1f0031c0","id":1339195,"name":"Trystan P\u00fctter","order":27,"profile_path":"\/tKJVa4wTNVTBuHjPJPBNCiYSPlD.jpg"},{"cast_id":79,"character":"Senior German Officer","credit_id":"56e1a19cc3a3680a0d002bdd","id":44637,"name":"Anian Zollner","order":28,"profile_path":"\/uuH5MNxSAqJQCCY0MCB74QrTAp6.jpg"},{"cast_id":81,"character":"German Officer","credit_id":"56e1a1ce925141543c000b43","id":71589,"name":"Hannes Wegener","order":30,"profile_path":"\/ku7c8L9GtTdfWhNXReFY05OHdw3.jpg"},{"cast_id":82,"character":"German Artillery Officer","credit_id":"56e1a236c3a3680a1f0031e6","id":21748,"name":"Maximilian Br\u00fcckner","order":31,"profile_path":"\/q0ghHkYgwc7qIednco8qxBJieDy.jpg"},{"cast_id":83,"character":"German Artillery Soldier","credit_id":"56e1a277925141088f002bc0","id":553003,"name":"Markus Tomczyk","order":32,"profile_path":null},{"cast_id":84,"character":"German Officer on Bridge","credit_id":"56e1a28fc3a3680a10002de0","id":147634,"name":"Peter Benedict","order":33,"profile_path":"\/wOtlAdtrcZc05Z1G6JlFUADiYFL.jpg"},{"cast_id":86,"character":"Junior German Officer","credit_id":"5776d2849251414643001641","id":1643968,"name":"Michael Kranz","order":34,"profile_path":"\/ksD74KqOB9SjOi40KrcqhR6aXIH.jpg"}],"crew":[{"credit_id":"52fe4928c3a36847f818c11d","department":"Directing","id":488,"job":"Director","name":"Steven Spielberg","profile_path":"\/pOK15UNaw75Bzj7BQO1ulehbPPm.jpg"},{"credit_id":"52fe4928c3a36847f818c137","department":"Writing","id":470,"job":"Screenplay","name":"Lee Hall","profile_path":null},{"credit_id":"52fe4928c3a36847f818c145","department":"Writing","id":7018,"job":"Writer","name":"Richard Curtis","profile_path":"\/uLjkovqtUtM4SckCFtrevZKKJNM.jpg"},{"credit_id":"52fe4929c3a36847f818c14b","department":"Editing","id":493,"job":"Editor","name":"Michael Kahn","profile_path":null},{"credit_id":"52fe4929c3a36847f818c151","department":"Camera","id":492,"job":"Director of Photography","name":"Janusz Kaminski","profile_path":"\/5LNGARjEfMDOcEP6fMNtJypAGYx.jpg"},{"credit_id":"55850a8b9251416b7b001a21","department":"Costume & Make-Up","id":498,"job":"Costume Design","name":"Joanna Johnston","profile_path":null},{"credit_id":"52fe4929c3a36847f818c15d","department":"Art","id":496,"job":"Production Design","name":"Rick Carter","profile_path":null},{"credit_id":"52fe4929c3a36847f818c16b","department":"Sound","id":491,"job":"Original Music Composer","name":"John Williams","profile_path":"\/d7NNRZQAIzLBSaoez550QHLpTk.jpg"},{"credit_id":"5385b3b00e0a261444001124","department":"Art","id":1325212,"job":"Set Decoration","name":"Lee Sandales","profile_path":null},{"credit_id":"5385b39c0e0a261441001168","department":"Art","id":11225,"job":"Art Direction","name":"Gary Tomkins","profile_path":null},{"credit_id":"5385b3580e0a2614530011bf","department":"Art","id":89385,"job":"Art Direction","name":"Hattie Storey","profile_path":null},{"credit_id":"5385b25d0e0a2614560010fe","department":"Production","id":489,"job":"Producer","name":"Kathleen Kennedy","profile_path":"\/uHEExgTTzJNDX1Gal9CW5n3QdEJ.jpg"},{"credit_id":"5385b2770e0a26144d00114e","department":"Production","id":488,"job":"Producer","name":"Steven Spielberg","profile_path":"\/pOK15UNaw75Bzj7BQO1ulehbPPm.jpg"},{"credit_id":"5385b28c0e0a26144a0010be","department":"Production","id":474,"job":"Casting","name":"Jina Jay","profile_path":"\/rMuj07hjZnT0zMC1kiBOs6IWCdO.jpg"},{"credit_id":"5385b3130e0a261456001108","department":"Art","id":10710,"job":"Art Direction","name":"Andrew Ackland-Snow","profile_path":null},{"credit_id":"5385b3280e0a26144d001155","department":"Art","id":89383,"job":"Art Direction","name":"Molly Hughes","profile_path":null},{"credit_id":"570b9958925141746d00019a","department":"Art","id":1325211,"job":"Supervising Art Director","name":"Neil Lamont","profile_path":null},{"credit_id":"5385b40d0e0a2614470010df","department":"Costume & Make-Up","id":1324461,"job":"Costume Supervisor","name":"David Crossman","profile_path":null},{"credit_id":"54759cb1c3a3687fd9000ced","department":"Art","id":1389524,"job":"Assistant Art Director","name":"Carmen Ruiz de Huidobro","profile_path":null},{"credit_id":"54759d0492514160e300321e","department":"Art","id":1389525,"job":"Art Department Coordinator","name":"Jodie Jackman","profile_path":null},{"credit_id":"54759d4292514144d50026cd","department":"Art","id":1389526,"job":"Construction Coordinator","name":"Amanda Pettett","profile_path":null},{"credit_id":"54759d949251414f19000477","department":"Crew","id":1334458,"job":"Property Master","name":"David Cheesman","profile_path":null},{"credit_id":"54759de2c3a3683012000374","department":"Sound","id":1338278,"job":"Boom Operator","name":"Orin Beaton","profile_path":null},{"credit_id":"54759e10c3a3687cfe001906","department":"Sound","id":7764,"job":"Supervising Sound Editor","name":"Richard Hymns","profile_path":null},{"credit_id":"54759e35925141407a001454","department":"Sound","id":2216,"job":"Supervising Sound Editor","name":"Gary Rydstrom","profile_path":"\/jZpr1nVfO7lldWI0YtmP1FGw7Rj.jpg"},{"credit_id":"54759e58c3a368764e00063a","department":"Sound","id":2216,"job":"Sound Designer","name":"Gary Rydstrom","profile_path":"\/jZpr1nVfO7lldWI0YtmP1FGw7Rj.jpg"},{"credit_id":"54759e90c3a3684df2000066","department":"Sound","id":8160,"job":"Foley","name":"Dennie Thorpe","profile_path":null},{"credit_id":"54759ea6c3a3686ba1001ee6","department":"Sound","id":8163,"job":"Foley","name":"Jana Vance","profile_path":null},{"credit_id":"54759ec4c3a3687cfe001939","department":"Editing","id":1389534,"job":"Dialogue Editor","name":"Richard Quinn","profile_path":null},{"credit_id":"54759ed892514160e3003258","department":"Editing","id":1376899,"job":"Dialogue Editor","name":"Cheryl Nardi","profile_path":null},{"credit_id":"54759f3bc3a36859b9001481","department":"Sound","id":3996,"job":"Sound Re-Recording Mixer","name":"Tom Johnson","profile_path":null},{"credit_id":"54759fa29251415273002056","department":"Crew","id":1389536,"job":"Special Effects Coordinator","name":"Anna Krawczyk","profile_path":null},{"credit_id":"5475a009c3a36830120003ce","department":"Visual Effects","id":1389537,"job":"Visual Effects Supervisor","name":"Ben Morris","profile_path":null},{"credit_id":"5475a043c3a3686ba1001f2a","department":"Crew","id":1389538,"job":"Stunt Coordinator","name":"Bryn Lawrence","profile_path":null},{"credit_id":"5475a06a925141527300206c","department":"Camera","id":40796,"job":"Still Photographer","name":"David Appleby","profile_path":null},{"credit_id":"5475a0a492514160e30032a6","department":"Camera","id":1386920,"job":"Still Photographer","name":"Andrew Cooper","profile_path":null},{"credit_id":"5475a0d192514166ba0000f2","department":"Lighting","id":1389540,"job":"Gaffer","name":"David Devlin","profile_path":null},{"credit_id":"5475a130c3a3687fd9000da0","department":"Lighting","id":1389541,"job":"Gaffer","name":"Eddie Knight","profile_path":null},{"credit_id":"5475a16cc3a368364c0024fa","department":"Production","id":4406,"job":"Casting","name":"Antoinette Boulat","profile_path":null},{"credit_id":"5475a18cc3a3687fd9000db5","department":"Production","id":4222,"job":"Casting","name":"Simone B\u00e4r","profile_path":null},{"credit_id":"5475a19e92514160e30032c6","department":"Production","id":1389542,"job":"Casting","name":"Alexandra Montag","profile_path":null},{"credit_id":"5475a1e2c3a368764e0006d2","department":"Costume & Make-Up","id":1389543,"job":"Set Costumer","name":"Calandra Meredith","profile_path":null},{"credit_id":"5475a22192514152730020ab","department":"Costume & Make-Up","id":1389544,"job":"Set Costumer","name":"Russell Barnett","profile_path":null},{"credit_id":"5475a23ec3a368764e0006de","department":"Costume & Make-Up","id":1389545,"job":"Set Costumer","name":"James Pavlou","profile_path":null},{"credit_id":"5475a27ec3a368364c002538","department":"Sound","id":21122,"job":"Music Editor","name":"Ramiro Belgardt","profile_path":null},{"credit_id":"5475a2bac3a3686ba1001f88","department":"Crew","id":1389546,"job":"Transportation Coordinator","name":"Holly Gray","profile_path":null},{"credit_id":"5475a304c3a3683012000451","department":"Crew","id":1389547,"job":"Dialect Coach","name":"Sandra Frieze","profile_path":null},{"credit_id":"5475a33bc3a3684df200012d","department":"Directing","id":1389548,"job":"Script Supervisor","name":"Anna Worley","profile_path":null}]},"images":{"backdrops":[{"aspect_ratio":1.7777777777778,"file_path":"\/iO4fslQ9CenAOcg3JfhN6o9va2.jpg","height":1080,"iso_639_1":null,"vote_average":5.530612244898,"vote_count":7,"width":1920},{"aspect_ratio":1.7777777777778,"file_path":"\/28FdskXalzOK0kEirQkmTRpnqR0.jpg","height":720,"iso_639_1":null,"vote_average":5.5072463768116,"vote_count":6,"width":1280},{"aspect_ratio":1.7777777777778,"file_path":"\/m2u5mH0Sxxw6Qg3dSqSueQ5Iztf.jpg","height":1080,"iso_639_1":"fr","vote_average":5.3447050461976,"vote_count":4,"width":1920},{"aspect_ratio":1.7777777777778,"file_path":"\/x3JblP6mAmbbfKX1964I4S9tgkx.jpg","height":1080,"iso_639_1":null,"vote_average":5.3447050461976,"vote_count":4,"width":1920},{"aspect_ratio":1.7777777777778,"file_path":"\/bvGFOiqgE6ljFLxP1xxUjYd94e3.jpg","height":1080,"iso_639_1":null,"vote_average":5.3125,"vote_count":1,"width":1920},{"aspect_ratio":1.7777777777778,"file_path":"\/k7v9S1DeRwPmqgp8CGgOEP9IojR.jpg","height":1080,"iso_639_1":null,"vote_average":5.3125,"vote_count":1,"width":1920},{"aspect_ratio":1.7777777777778,"file_path":"\/lVz03rNHtZrjbrvixI6icy8u1Y9.jpg","height":720,"iso_639_1":null,"vote_average":5.3125,"vote_count":1,"width":1280},{"aspect_ratio":1.7777777777778,"file_path":"\/8HdXRgzALHM3uLmlIxrl5kM11oc.jpg","height":1080,"iso_639_1":null,"vote_average":5.3125,"vote_count":1,"width":1920},{"aspect_ratio":1.7777777777778,"file_path":"\/g7i1GTucvhOil3TLEA5EdAFONZ3.jpg","height":1080,"iso_639_1":null,"vote_average":5.2380952380952,"vote_count":2,"width":1920},{"aspect_ratio":1.7777777777778,"file_path":"\/pAwH05ik5AVq5lJaMWs2DoJcOui.jpg","height":1080,"iso_639_1":null,"vote_average":5.2380952380952,"vote_count":2,"width":1920},{"aspect_ratio":1.7777777777778,"file_path":"\/bBgdA8sIGiDC85PGhNAtt9Abn6V.jpg","height":1080,"iso_639_1":null,"vote_average":5.2380952380952,"vote_count":2,"width":1920},{"aspect_ratio":1.7777777777778,"file_path":"\/uXq2KY4mESfJQsj2YHkkkv9mbTT.jpg","height":1080,"iso_639_1":null,"vote_average":5.2380952380952,"vote_count":2,"width":1920},{"aspect_ratio":1.7777777777778,"file_path":"\/8gQDKwSljRUlT9gyFm2c5PhfmaQ.jpg","height":1080,"iso_639_1":null,"vote_average":5.2380952380952,"vote_count":2,"width":1920},{"aspect_ratio":1.7777777777778,"file_path":"\/NxWjw67FlafIfk2KmGZ1gUSGYN.jpg","height":1080,"iso_639_1":null,"vote_average":5.2307692307692,"vote_count":2,"width":1920},{"aspect_ratio":1.7777777777778,"file_path":"\/28aH57TP7huPxxX73COrd2xlRwJ.jpg","height":1080,"iso_639_1":null,"vote_average":5.2161172161172,"vote_count":2,"width":1920},{"aspect_ratio":1.7777777777778,"file_path":"\/5xEp14rTh4OIWWbNTJTCgQssewA.jpg","height":1080,"iso_639_1":null,"vote_average":5.2161172161172,"vote_count":2,"width":1920},{"aspect_ratio":1.7777777777778,"file_path":"\/6G0ORMwXitjoi2q2GqbRpOAdbHe.jpg","height":1080,"iso_639_1":null,"vote_average":5.2161172161172,"vote_count":2,"width":1920},{"aspect_ratio":1.7777777777778,"file_path":"\/pQfiWz19q6Nfb2q8VDJNRy0bs2a.jpg","height":1080,"iso_639_1":null,"vote_average":5.2161172161172,"vote_count":2,"width":1920}],"posters":[{"aspect_ratio":0.66666666666667,"file_path":"\/6wMoQyJddEiLCzLUHiX7LNWhDol.jpg","height":1500,"iso_639_1":"en","vote_average":5.7266542980829,"vote_count":14,"width":1000},{"aspect_ratio":0.66666666666667,"file_path":"\/1QzG1m0oDro2QTGnOpwFNbIAHLP.jpg","height":1500,"iso_639_1":"fr","vote_average":5.3846153846154,"vote_count":2,"width":1000},{"aspect_ratio":0.7,"file_path":"\/vngh0Sg1xsaj3uHySqkeonKeNYB.jpg","height":1500,"iso_639_1":"it","vote_average":5.3174603174603,"vote_count":3,"width":1050},{"aspect_ratio":0.66666666666667,"file_path":"\/xDrNkn88Sh6Gm3fFUwFQl6CtXub.jpg","height":3000,"iso_639_1":"ru","vote_average":5.3125,"vote_count":1,"width":2000},{"aspect_ratio":0.66666666666667,"file_path":"\/tKuBbV3TMnUWgvIlHKeKLfhPTJB.jpg","height":1500,"iso_639_1":"en","vote_average":5.3125,"vote_count":1,"width":1000},{"aspect_ratio":0.66666666666667,"file_path":"\/b3fFM8kgksqc237YumpjlKgrJHI.jpg","height":3000,"iso_639_1":"en","vote_average":5.3125,"vote_count":1,"width":2000},{"aspect_ratio":0.66666666666667,"file_path":"\/wMYFNgwYh6NvSeVsOyL8L6lSSde.jpg","height":1500,"iso_639_1":"en","vote_average":5.3125,"vote_count":1,"width":1000},{"aspect_ratio":0.66666666666667,"file_path":"\/y02TLJAlRQglmFGX6jd9fiUBDCc.jpg","height":2817,"iso_639_1":"de","vote_average":5.3125,"vote_count":1,"width":1878},{"aspect_ratio":0.7,"file_path":"\/khxOja84TXsQVKt9aQfbCyqBYmh.jpg","height":1500,"iso_639_1":"en","vote_average":5.2587991718427,"vote_count":6,"width":1050},{"aspect_ratio":0.66666666666667,"file_path":"\/8uTobfUIa2FlbG7C9sfqoLwTk2F.jpg","height":1500,"iso_639_1":"fr","vote_average":5.2454212454212,"vote_count":2,"width":1000},{"aspect_ratio":0.75265392781316,"file_path":"\/icrVSAj2lNqKm6dpMMIasL251lW.jpg","height":942,"iso_639_1":"cs","vote_average":5.2380952380952,"vote_count":2,"width":709},{"aspect_ratio":0.6768,"file_path":"\/zlh6w8fGQZ5HEY2XEZjsfIr9FM0.jpg","height":3750,"iso_639_1":"en","vote_average":5.2173913043478,"vote_count":6,"width":2538},{"aspect_ratio":0.66666666666667,"file_path":"\/pCfqNRABBSLHA1ZAMQemfmsEi6e.jpg","height":1500,"iso_639_1":"de","vote_average":5.2161172161172,"vote_count":2,"width":1000},{"aspect_ratio":0.85446009389671,"file_path":"\/xVo3wf8mvX9shf17z3Y2WqdknVC.jpg","height":1278,"iso_639_1":"en","vote_average":5.1868131868132,"vote_count":2,"width":1092},{"aspect_ratio":0.69095477386935,"file_path":"\/2PszpoQfiIemvwPE1yqqqD8W3z7.jpg","height":796,"iso_639_1":"yi","vote_average":5.1803751803752,"vote_count":3,"width":550},{"aspect_ratio":0.70041039671683,"file_path":"\/66YrcdDFJfq5s7WCpuhscWb0Cxl.jpg","height":1462,"iso_639_1":"es","vote_average":5.1785714285714,"vote_count":1,"width":1024},{"aspect_ratio":0.67453625632378,"file_path":"\/a3TkCK7pkuxOhJoUtxUlbmzpoUm.jpg","height":593,"iso_639_1":"es","vote_average":5.1711309523809,"vote_count":1,"width":400},{"aspect_ratio":0.69808027923211,"file_path":"\/z39O5hNmo1KhbauwetD7YO9V3yP.jpg","height":1146,"iso_639_1":"uk","vote_average":5.1711309523809,"vote_count":1,"width":800},{"aspect_ratio":0.706,"file_path":"\/3e0iBNHN4i0dwsUQsIArWGFVcCc.jpg","height":1500,"iso_639_1":"fr","vote_average":5.1711309523809,"vote_count":1,"width":1059},{"aspect_ratio":0.75338345864662,"file_path":"\/xe1YYcrVwShtlEyZUf5kI93Yyfo.jpg","height":665,"iso_639_1":"fr","vote_average":5.1711309523809,"vote_count":1,"width":501},{"aspect_ratio":0.68,"file_path":"\/pb8TVrXAJ3j6JgMhAW2QHqr0yga.jpg","height":1100,"iso_639_1":"ru","vote_average":5.1243781094527,"vote_count":4,"width":748},{"aspect_ratio":0.70714285714286,"file_path":"\/AppJL230EO7mFdxdlryJx72Af5v.jpg","height":1400,"iso_639_1":"de","vote_average":5.1062271062271,"vote_count":2,"width":990},{"aspect_ratio":0.66666666666667,"file_path":"\/kOSqA0xeA34wC6eIIhzecY1Wwct.jpg","height":1500,"iso_639_1":"ko","vote_average":0,"vote_count":0,"width":1000},{"aspect_ratio":0.70469798657718,"file_path":"\/2y126f2wPmH8LDxLjpycYYrZm2V.jpg","height":2235,"iso_639_1":"ro","vote_average":0,"vote_count":0,"width":1575},{"aspect_ratio":0.69660861594867,"file_path":"\/w2i6Rc5EBctfoECpSHlI5TGWYX3.jpg","height":1091,"iso_639_1":"he","vote_average":0,"vote_count":0,"width":760},{"aspect_ratio":0.70391061452514,"file_path":"\/6KFfCSmK3D8fv09suZDaUTISXOZ.jpg","height":1074,"iso_639_1":"pt","vote_average":0,"vote_count":0,"width":756},{"aspect_ratio":0.70671378091873,"file_path":"\/apK7KNNRsKZIsVYqbXt5tvcpn6P.jpg","height":566,"iso_639_1":"hu","vote_average":0,"vote_count":0,"width":400},{"aspect_ratio":0.66666666666667,"file_path":"\/qGe9ryDoYsV3sMzL8HdHXOUy8we.jpg","height":1500,"iso_639_1":"xx","vote_average":0,"vote_count":0,"width":1000},{"aspect_ratio":0.70671378091873,"file_path":"\/u2ILQZGejVYDSLEZNGRUs9puSYm.jpg","height":566,"iso_639_1":"gl","vote_average":0,"vote_count":0,"width":400}]}}