{"adult":false,"backdrop_path":"\/wOtuap05bz3AJy0URt8wMsqC2Ml.jpg","belongs_to_collection":null,"budget":10000000,"genres":[{"id":18,"name":"Drama"},{"id":35,"name":"Comedy"},{"id":10749,"name":"Romance"}],"homepage":"http:\/\/www.dostanathefilm.com\/","id":14071,"imdb_id":"tt1185420","original_language":"hi","original_title":"Dostana","overview":"Kunal and Sameer, two straight guys who pretend to be a gay couple to secure an posh Miami apartment, but both of them fall for their gorgeous room-mate Neha, hilarity ensures as they strive to convince one and all they are gay! While secretly trying to win Neha's heart.","popularity":0.533274,"poster_path":"\/n5zfjcXhME7VjMlC4vDt8gQ5zUn.jpg","production_companies":[{"name":"Yash Raj Films","id":1569},{"name":"Dharma Productions","id":19146},{"name":"ShowMan Pictures","id":82555}],"production_countries":[{"iso_3166_1":"IN","name":"India"}],"release_date":"2008-11-12","revenue":20000000,"runtime":142,"spoken_languages":[{"iso_639_1":"en","name":"English"},{"iso_639_1":"hi","name":"\u0939\u093f\u0928\u094d\u0926\u0940"},{"iso_639_1":"it","name":"Italiano"}],"status":"Released","tagline":"A story about two guys... a girl... and one little lie. Believe it!","title":"Dostana","video":false,"vote_average":6.4,"vote_count":24,"credits":{"cast":[{"cast_id":1,"character":"Kunal","credit_id":"52fe45c99251416c7506269d","id":52971,"name":"John Abraham","order":0,"profile_path":"\/u7nDGaIjmh5PVBzCqpJRwUT9qQH.jpg"},{"cast_id":2,"character":"Neha","credit_id":"52fe45c99251416c750626a1","id":77234,"name":"Priyanka Chopra","order":1,"profile_path":"\/x0qfELMntDts8iDlEioL98DRpHy.jpg"},{"cast_id":3,"character":"Abhimanyu Singh","credit_id":"52fe45c99251416c750626a5","id":77235,"name":"Bobby Deol","order":2,"profile_path":"\/7dVbYjjnpzR8mSvzahihiImTwoW.jpg"},{"cast_id":4,"character":"Sameer","credit_id":"52fe45c99251416c750626a9","id":35793,"name":"Abhishek Bachchan","order":3,"profile_path":"\/1rsgbAdguvxIMHHHNlxQHZYUAVr.jpg"},{"cast_id":5,"character":"Item Number- Shut Up & Bounce","credit_id":"52fe45c99251416c750626ad","id":86060,"name":"Shilpa Shetty","order":4,"profile_path":"\/npc5AI3ZPTaBiZ0Te427sNXDEFJ.jpg"},{"cast_id":6,"character":"M","credit_id":"52fe45c99251416c750626b1","id":35779,"name":"Boman Irani","order":5,"profile_path":"\/ybhFam8adUpWz3Re49T8uDm8DcT.jpg"},{"cast_id":7,"character":"Seema Acharya (Sameer's mother)","credit_id":"52fe45c99251416c750626b5","id":35777,"name":"Kiron Kher","order":6,"profile_path":"\/wZ1sz7mnCclTEt0zV9EcQJgmTQY.jpg"},{"cast_id":11,"character":"Ms. Melwani","credit_id":"52fe45c99251416c750626cb","id":85734,"name":"Sushmita Mukherjee","order":7,"profile_path":"\/pNPjhJLFyzZMASL8ZXWCDo6JuZe.jpg"},{"cast_id":12,"character":"Anaita","credit_id":"5808ac179251410f570079db","id":1697111,"name":"Monika Gaba","order":8,"profile_path":null}],"crew":[{"credit_id":"52fe45c99251416c750626bb","department":"Directing","id":146975,"job":"Director","name":"Tarun Mansukhani","profile_path":null},{"credit_id":"5808ac8c9251410f9d007e27","department":"Writing","id":146975,"job":"Screenplay","name":"Tarun Mansukhani","profile_path":null},{"credit_id":"5808ac4e9251410fe3007acc","department":"Production","id":1035367,"job":"Producer","name":"Hiroo Yash Johar","profile_path":null},{"credit_id":"5808ac5b92514110280077d2","department":"Production","id":35736,"job":"Producer","name":"Karan Johar","profile_path":"\/pFWDjH57HsdkEKM8HT2wlH2Ahcw.jpg"},{"credit_id":"5808aca0c3a368752b0076f1","department":"Writing","id":146975,"job":"Story","name":"Tarun Mansukhani","profile_path":null},{"credit_id":"5808acb7c3a36874ca007985","department":"Sound","id":1696256,"job":"Songs","name":"Vishal\u2013Shekhar","profile_path":null},{"credit_id":"5808acc9c3a368672f007176","department":"Sound","id":568674,"job":"Music","name":"Salim-Sulaiman","profile_path":null},{"credit_id":"5808acde9251410fe3007b20","department":"Editing","id":232526,"job":"Editor","name":"Manan Sagar","profile_path":null}]},"images":{"backdrops":[{"aspect_ratio":1.7777777777778,"file_path":"\/wOtuap05bz3AJy0URt8wMsqC2Ml.jpg","height":720,"iso_639_1":null,"vote_average":5.3050595238095,"vote_count":1,"width":1280},{"aspect_ratio":1.7777777777778,"file_path":"\/tAsuEDhQ5otYs80BuQvAioebuWl.jpg","height":1080,"iso_639_1":null,"vote_average":0,"vote_count":0,"width":1920},{"aspect_ratio":1.7777777777778,"file_path":"\/ic8Jc3m9Fd5JIE2yJwjmgXCKvO0.jpg","height":1080,"iso_639_1":null,"vote_average":0,"vote_count":0,"width":1920},{"aspect_ratio":1.7777777777778,"file_path":"\/7hpzBpv0IXB2NscGYlKHTksN6JN.jpg","height":720,"iso_639_1":null,"vote_average":0,"vote_count":0,"width":1280},{"aspect_ratio":1.7777777777778,"file_path":"\/9Ea3kH5AkKSP3q3B9AeLwzDBD5w.jpg","height":720,"iso_639_1":null,"vote_average":0,"vote_count":0,"width":1280},{"aspect_ratio":1.7777777777778,"file_path":"\/v2hWWRoNQ3pgbGnrG8I6b2x9j63.jpg","height":720,"iso_639_1":null,"vote_average":0,"vote_count":0,"width":1280},{"aspect_ratio":1.7777777777778,"file_path":"\/2pBc1fVmPYG6K5COtcMEdPI0z9e.jpg","height":1080,"iso_639_1":null,"vote_average":0,"vote_count":0,"width":1920},{"aspect_ratio":1.7763888888889,"file_path":"\/7rAimaF3Wv0BXdOokoDCVCgoJW3.jpg","height":720,"iso_639_1":null,"vote_average":0,"vote_count":0,"width":1279}],"posters":[{"aspect_ratio":0.80527086383602,"file_path":"\/n5zfjcXhME7VjMlC4vDt8gQ5zUn.jpg","height":683,"iso_639_1":"en","vote_average":5.3125,"vote_count":1,"width":550},{"aspect_ratio":0.69060773480663,"file_path":"\/azJwCYuWEcOOK8hQJPsttnBxgOE.jpg","height":724,"iso_639_1":"en","vote_average":5.3050595238095,"vote_count":1,"width":500},{"aspect_ratio":0.69060773480663,"file_path":"\/1eR7aeu01cMdspnhph6fTZIzPWV.jpg","height":724,"iso_639_1":"en","vote_average":5.2529761904762,"vote_count":1,"width":500},{"aspect_ratio":0.70621468926554,"file_path":"\/n4f5FMcPpd0JCCWUCswyJQfFnZF.jpg","height":708,"iso_639_1":"de","vote_average":0,"vote_count":0,"width":500},{"aspect_ratio":0.69060773480663,"file_path":"\/1QDC5I5qv8wJJNniBhOo14wJbRL.jpg","height":724,"iso_639_1":"en","vote_average":0,"vote_count":0,"width":500}]}}