{"adult":false,"backdrop_path":null,"belongs_to_collection":null,"budget":0,"genres":[],"homepage":"","id":296892,"imdb_id":"tt4010306","original_language":"en","original_title":"Jigariyaa","overview":"Shaamu falls in love with Raadha at first sight. As they grow close to each other, destiny takes another turn.","popularity":0.004562,"poster_path":"\/eRuWI6zd8jtkKspDpZk2bNpjwcw.jpg","production_companies":[],"production_countries":[],"release_date":"2014-10-10","revenue":0,"runtime":0,"spoken_languages":[],"status":"Released","tagline":"","title":"Jigariyaa","video":true,"vote_average":0,"vote_count":0,"credits":{"cast":[{"cast_id":0,"character":"Raadha","credit_id":"5437bb9bc3a36825ba000db9","id":1372696,"name":"Cherry Mardia","order":1,"profile_path":null},{"cast_id":2,"character":"Shaamu","credit_id":"5437bd60c3a3684d2500180b","id":1372697,"name":"Harshvardhan Deo","order":2,"profile_path":null}],"crew":[{"credit_id":"5437bd420e0a264a45001858","department":"Directing","id":1267404,"job":"Director","name":"Raj Purohit","profile_path":null}]},"images":{"backdrops":[],"posters":[{"aspect_ratio":0.64285714285714,"file_path":"\/eRuWI6zd8jtkKspDpZk2bNpjwcw.jpg","height":910,"iso_639_1":null,"vote_average":5.2752976190476,"vote_count":1,"width":585}]}}